[{"id":"WEST_68TH_STREET_COLUMBUS_AVENUE_CENTRAL_PARK_WEST_S_4","street":"WEST 68TH STREET","from":"COLUMBUS AVENUE","to":"CENTRAL PARK WEST","side":"S","line":[[40.774392,-73.979504],[40.77428,-73.979239]],"rules":[{"category":"NO_PARKING","description":"NO PARKING MONDAY-FRIDAY 8AM-4PM --> (SUPERSEDES SP-121CA)","days":[1,2,3,4,5],"timeRanges":[{"start":480,"end":960}],"anytime":false,"arrow":"towards"}],"dominantCategory":"NO_PARKING"},{"id":"WEST_68TH_STREET_COLUMBUS_AVENUE_CENTRAL_PARK_WEST_S_5","street":"WEST 68TH STREET","from":"COLUMBUS AVENUE","to":"CENTRAL PARK WEST","side":"S","line":[[40.77428,-73.979239],[40.774197,-73.979043]],"rules":[{"category":"NO_PARKING","description":"NO PARKING MONDAY-FRIDAY 8AM-4PM --> (SUPERSEDES SP-121CA)","days":[1,2,3,4,5],"timeRanges":[{"start":480,"end":960}],"anytime":false,"arrow":"towards"}],"dominantCategory":"NO_PARKING"},{"id":"WEST_68TH_STREET_COLUMBUS_AVENUE_CENTRAL_PARK_WEST_S_6","street":"WEST 68TH STREET","from":"COLUMBUS AVENUE","to":"CENTRAL PARK WEST","side":"S","line":[[40.774197,-73.979043],[40.774039,-73.978671]],"rules":[{"category":"NO_PARKING","description":"NO PARKING ANYTIME --> (SUPERSEDES SP-854CA)","days":[0,1,2,3,4,5,6],"timeRanges":[],"anytime":true,"arrow":"towards"},{"category":"ASP_TUE_FRI","description":"NO PARKING (SANITATION BROOM SYMBOL) TUESDAY FRIDAY 8AM-9:30AM <-> (SUPERSEDES SP-844C)","days":[2,5],"timeRanges":[{"start":480,"end":570}],"anytime":false,"arrow":"both"}],"dominantCategory":"NO_PARKING"},{"id":"WEST_68TH_STREET_COLUMBUS_AVENUE_CENTRAL_PARK_WEST_S_7","street":"WEST 68TH STREET","from":"COLUMBUS AVENUE","to":"CENTRAL PARK WEST","side":"S","line":[[40.774039,-73.978671],[40.773956,-73.978473],[40.773943,-73.978444]],"rules":[{"category":"ASP_TUE_FRI","description":"NO PARKING (SANITATION BROOM SYMBOL) TUESDAY FRIDAY 8AM-9:30AM <-> (SUPERSEDES SP-844C)","days":[2,5],"timeRanges":[{"start":480,"end":570}],"anytime":false,"arrow":"both"}],"dominantCategory":"ASP_TUE_FRI"},{"id":"WEST_68TH_STREET_COLUMBUS_AVENUE_CENTRAL_PARK_WEST_S_8","street":"WEST 68TH STREET","from":"COLUMBUS AVENUE","to":"CENTRAL PARK WEST","side":"S","line":[[40.773943,-73.978444],[40.773844,-73.978206]],"rules":[{"category":"ASP_TUE_FRI","description":"NO PARKING (SANITATION BROOM SYMBOL) TUESDAY FRIDAY 8AM-9:30AM --> (SUPERSEDES SP-844CA)","days":[2,5],"timeRanges":[{"start":480,"end":570}],"anytime":false,"arrow":"towards"}],"dominantCategory":"ASP_TUE_FRI"},{"id":"WEST_68TH_STREET_COLUMBUS_AVENUE_CENTRAL_PARK_WEST_S_9","street":"WEST 68TH STREET","from":"COLUMBUS AVENUE","to":"CENTRAL PARK WEST","side":"S","line":[[40.773844,-73.978206],[40.773791,-73.97808]],"rules":[{"category":"ASP_TUE_FRI","description":"NO PARKING (SANITATION BROOM SYMBOL) TUESDAY FRIDAY 8AM-9:30AM --> (SUPERSEDES SP-844CA)","days":[2,5],"timeRanges":[{"start":480,"end":570}],"anytime":false,"arrow":"towards"},{"category":"NO_PARKING","description":"NO PARKING ANYTIME --> (SUPERSEDES SP-854CA)","days":[0,1,2,3,4,5,6],"timeRanges":[],"anytime":true,"arrow":"towards"}],"dominantCategory":"NO_PARKING"},{"id":"WEST_67TH_STREET_CENTRAL_PARK_WEST_COLUMBUS_AVENUE_N_0","street":"WEST 67TH STREET","from":"CENTRAL PARK WEST","to":"COLUMBUS AVENUE","side":"N","line":[[40.772996,-73.978113],[40.773056,-73.978253],[40.773101,-73.978351]],"rules":[{"category":"ASP_MON_THU","description":"NO PARKING (SANITATION BROOM SYMBOL) MONDAY THURSDAY 8AM-9:30AM <-> (SUPERSEDES SP-412C)","days":[1,4],"timeRanges":[{"start":480,"end":570}],"anytime":false,"arrow":"both"}],"dominantCategory":"ASP_MON_THU"},{"id":"WEST_67TH_STREET_CENTRAL_PARK_WEST_COLUMBUS_AVENUE_N_1","street":"WEST 67TH STREET","from":"CENTRAL PARK WEST","to":"COLUMBUS AVENUE","side":"N","line":[[40.773101,-73.978351],[40.773106,-73.978363],[40.773222,-73.97865]],"rules":[{"category":"ASP_MON_THU","description":"NO PARKING (SANITATION BROOM SYMBOL) MONDAY THURSDAY 8AM-9:30AM <-> (SUPERSEDES SP-412C)","days":[1,4],"timeRanges":[{"start":480,"end":570}],"anytime":false,"arrow":"both"}],"dominantCategory":"ASP_MON_THU"},{"id":"WEST_67TH_STREET_CENTRAL_PARK_WEST_COLUMBUS_AVENUE_N_2","street":"WEST 67TH STREET","from":"CENTRAL PARK WEST","to":"COLUMBUS AVENUE","side":"N","line":[[40.773222,-73.97865],[40.773283,-73.978799]],"rules":[{"category":"ASP_MON_THU","description":"NO PARKING (SANITATION BROOM SYMBOL) MONDAY THURSDAY 8AM-9:30AM --> (SUPERSEDES SP-412CA)","days":[1,4],"timeRanges":[{"start":480,"end":570}],"anytime":false,"arrow":"towards"}],"dominantCategory":"ASP_MON_THU"},{"id":"WEST_67TH_STREET_CENTRAL_PARK_WEST_COLUMBUS_AVENUE_N_3","street":"WEST 67TH STREET","from":"CENTRAL PARK WEST","to":"COLUMBUS AVENUE","side":"N","line":[[40.773283,-73.978799],[40.773455,-73.979223],[40.773548,-73.979441]],"rules":[{"category":"NO_PARKING","description":"NO PARKING ANYTIME --> (SUPERSEDES SP-854CA)","days":[0,1,2,3,4,5,6],"timeRanges":[],"anytime":true,"arrow":"towards"},{"category":"ASP_MON_THU","description":"NO PARKING (SANITATION BROOM SYMBOL) MONDAY THURSDAY 8AM-9:30AM <-> (SUPERSEDES SP-412C)","days":[1,4],"timeRanges":[{"start":480,"end":570}],"anytime":false,"arrow":"both"}],"dominantCategory":"NO_PARKING"},{"id":"CENTRAL_PARK_WEST_WEST_67TH_STREET_WEST_72ND_STREET_E_0","street":"CENTRAL PARK WEST","from":"WEST 67TH STREET","to":"WEST 72ND STREET","side":"E","line":[[40.773013,-73.978172],[40.773174,-73.978064]],"rules":[{"category":"NO_STANDING","description":"NO STOPPING ANYTIME <-> (SUPERSEDES SP-14A)","days":[0,1,2,3,4,5,6],"timeRanges":[],"anytime":true,"arrow":"both"}],"dominantCategory":"NO_STANDING"},{"id":"CENTRAL_PARK_WEST_WEST_67TH_STREET_WEST_72ND_STREET_E_1","street":"CENTRAL PARK WEST","from":"WEST 67TH STREET","to":"WEST 72ND STREET","side":"E","line":[[40.773174,-73.978064],[40.773528,-73.977826]],"rules":[{"category":"NO_STANDING","description":"NO STOPPING ANYTIME <-> (SUPERSEDES SP-14A)","days":[0,1,2,3,4,5,6],"timeRanges":[],"anytime":true,"arrow":"both"},{"category":"NO_STANDING","description":"NO STOPPING ANYTIME <-> (SUPERSEDES SP-14A)","days":[0,1,2,3,4,5,6],"timeRanges":[],"anytime":true,"arrow":"both"}],"dominantCategory":"NO_STANDING"},{"id":"CENTRAL_PARK_WEST_WEST_67TH_STREET_WEST_72ND_STREET_E_2","street":"CENTRAL PARK WEST","from":"WEST 67TH STREET","to":"WEST 72ND STREET","side":"E","line":[[40.773528,-73.977826],[40.773862,-73.9776]],"rules":[{"category":"NO_STANDING","description":"NO STOPPING ANYTIME <-> (SUPERSEDES SP-14A)","days":[0,1,2,3,4,5,6],"timeRanges":[],"anytime":true,"arrow":"both"},{"category":"NO_STANDING","description":"NO STOPPING ANYTIME <-> (SUPERSEDES SP-14A)","days":[0,1,2,3,4,5,6],"timeRanges":[],"anytime":true,"arrow":"both"}],"dominantCategory":"NO_STANDING"},{"id":"CENTRAL_PARK_WEST_WEST_67TH_STREET_WEST_72ND_STREET_E_3","street":"CENTRAL PARK WEST","from":"WEST 67TH STREET","to":"WEST 72ND STREET","side":"E","line":[[40.773862,-73.9776],[40.774184,-73.977384]],"rules":[{"category":"NO_STANDING","description":"NO STOPPING ANYTIME <-> (SUPERSEDES SP-14A)","days":[0,1,2,3,4,5,6],"timeRanges":[],"anytime":true,"arrow":"both"},{"category":"NO_STANDING","description":"NO STOPPING ANYTIME <-> (SUPERSEDES SP-14A)","days":[0,1,2,3,4,5,6],"timeRanges":[],"anytime":true,"arrow":"both"}],"dominantCategory":"NO_STANDING"},{"id":"CENTRAL_PARK_WEST_WEST_67TH_STREET_WEST_72ND_STREET_E_4","street":"CENTRAL PARK WEST","from":"WEST 67TH STREET","to":"WEST 72ND STREET","side":"E","line":[[40.774184,-73.977384],[40.774616,-73.977093]],"rules":[{"category":"NO_STANDING","description":"NO STOPPING ANYTIME <-> (SUPERSEDES SP-14A)","days":[0,1,2,3,4,5,6],"timeRanges":[],"anytime":true,"arrow":"both"},{"category":"NO_STANDING","description":"BUS STOP SIGN (BUS & HANDICAP SYMBOLS) NO STANDING W/ SINGLE ARROW","days":[1,2,3,4,5,6],"timeRanges":[],"anytime":false,"arrow":null}],"dominantCategory":"NO_STANDING"},{"id":"WEST_69TH_STREET_CENTRAL_PARK_WEST_COLUMBUS_AVENUE_S_0","street":"WEST 69TH STREET","from":"CENTRAL PARK WEST","to":"COLUMBUS AVENUE","side":"S","line":[[40.774275,-73.977407],[40.774325,-73.977527],[40.774364,-73.977622]],"rules":[{"category":"ASP_TUE_FRI","description":"NO PARKING (SANITATION BROOM SYMBOL) TUESDAY FRIDAY 8AM-9:30AM <-> (SUPERSEDES SP-844C)","days":[2,5],"timeRanges":[{"start":480,"end":570}],"anytime":false,"arrow":"both"},{"category":"ASP_TUE_FRI","description":"NO PARKING (SANITATION BROOM SYMBOL) TUESDAY FRIDAY 8AM-9:30AM <-> (SUPERSEDES SP-844C)","days":[2,5],"timeRanges":[{"start":480,"end":570}],"anytime":false,"arrow":"both"}],"dominantCategory":"ASP_TUE_FRI"},{"id":"WEST_69TH_STREET_CENTRAL_PARK_WEST_COLUMBUS_AVENUE_S_1","street":"WEST 69TH STREET","from":"CENTRAL PARK WEST","to":"COLUMBUS AVENUE","side":"S","line":[[40.774364,-73.977622],[40.774522,-73.977999]],"rules":[{"category":"ASP_TUE_FRI","description":"NO PARKING (SANITATION BROOM SYMBOL) TUESDAY FRIDAY 8AM-9:30AM <-> (SUPERSEDES SP-844C)","days":[2,5],"timeRanges":[{"start":480,"end":570}],"anytime":false,"arrow":"both"},{"category":"ASP_TUE_FRI","description":"NO PARKING (SANITATION BROOM SYMBOL) TUESDAY FRIDAY 8AM-9:30AM <-> (SUPERSEDES SP-844C)","days":[2,5],"timeRanges":[{"start":480,"end":570}],"anytime":false,"arrow":"both"},{"category":"ASP_TUE_FRI","description":"NO PARKING (SANITATION BROOM SYMBOL) TUESDAY FRIDAY 8AM-9:30AM <-> (SUPERSEDES SP-844C)","days":[2,5],"timeRanges":[{"start":480,"end":570}],"anytime":false,"arrow":"both"}],"dominantCategory":"ASP_TUE_FRI"},{"id":"WEST_69TH_STREET_CENTRAL_PARK_WEST_COLUMBUS_AVENUE_S_2","street":"WEST 69TH STREET","from":"CENTRAL PARK WEST","to":"COLUMBUS AVENUE","side":"S","line":[[40.774522,-73.977999],[40.774651,-73.97831]],"rules":[{"category":"ASP_TUE_FRI","description":"NO PARKING (SANITATION BROOM SYMBOL) TUESDAY FRIDAY 8AM-9:30AM <-> (SUPERSEDES SP-844C)","days":[2,5],"timeRanges":[{"start":480,"end":570}],"anytime":false,"arrow":"both"},{"category":"ASP_TUE_FRI","description":"NO PARKING (SANITATION BROOM SYMBOL) TUESDAY FRIDAY 8AM-9:30AM <-> (SUPERSEDES SP-844C)","days":[2,5],"timeRanges":[{"start":480,"end":570}],"anytime":false,"arrow":"both"}],"dominantCategory":"ASP_TUE_FRI"},{"id":"WEST_69TH_STREET_CENTRAL_PARK_WEST_COLUMBUS_AVENUE_S_3","street":"WEST 69TH STREET","from":"CENTRAL PARK WEST","to":"COLUMBUS AVENUE","side":"S","line":[[40.774651,-73.97831],[40.774857,-73.978804]],"rules":[{"category":"ASP_TUE_FRI","description":"NO PARKING (SANITATION BROOM SYMBOL) TUESDAY FRIDAY 8AM-9:30AM <-> (SUPERSEDES SP-844C)","days":[2,5],"timeRanges":[{"start":480,"end":570}],"anytime":false,"arrow":"both"},{"category":"ASP_TUE_FRI","description":"NO PARKING (SANITATION BROOM SYMBOL) TUESDAY FRIDAY 8AM-9:30AM <-> (SUPERSEDES SP-844C)","days":[2,5],"timeRanges":[{"start":480,"end":570}],"anytime":false,"arrow":"both"}],"dominantCategory":"ASP_TUE_FRI"},{"id":"WEST_69TH_STREET_CENTRAL_PARK_WEST_COLUMBUS_AVENUE_S_4","street":"WEST 69TH STREET","from":"CENTRAL PARK WEST","to":"COLUMBUS AVENUE","side":"S","line":[[40.774857,-73.978804],[40.775023,-73.979203]],"rules":[{"category":"ASP_TUE_FRI","description":"NO PARKING (SANITATION BROOM SYMBOL) TUESDAY FRIDAY 8AM-9:30AM <-> (SUPERSEDES SP-844C)","days":[2,5],"timeRanges":[{"start":480,"end":570}],"anytime":false,"arrow":"both"},{"category":"ASP_TUE_FRI","description":"NO PARKING (SANITATION BROOM SYMBOL) TUESDAY FRIDAY 8AM-9:30AM <-> (SUPERSEDES SP-844C)","days":[2,5],"timeRanges":[{"start":480,"end":570}],"anytime":false,"arrow":"both"}],"dominantCategory":"ASP_TUE_FRI"},{"id":"WEST_70TH_STREET_COLUMBUS_AVENUE_CENTRAL_PARK_WEST_N_6","street":"WEST 70TH STREET","from":"COLUMBUS AVENUE","to":"CENTRAL PARK WEST","side":"N","line":[[40.775156,-73.977555],[40.775022,-73.977236]],"rules":[{"category":"ASP_MON_THU","description":"NO PARKING (SANITATION BROOM SYMBOL) MONDAY THURSDAY 9AM-10:30AM <-> (SUPERSEDES SP-413C)","days":[1,4],"timeRanges":[{"start":540,"end":630}],"anytime":false,"arrow":"both"},{"category":"ASP_MON_THU","description":"NO PARKING (SANITATION BROOM SYMBOL) MONDAY THURSDAY 9AM-10:30AM <-> (SUPERSEDES SP-413C)","days":[1,4],"timeRanges":[{"start":540,"end":630}],"anytime":false,"arrow":"both"}],"dominantCategory":"ASP_MON_THU"},{"id":"WEST_70TH_STREET_COLUMBUS_AVENUE_CENTRAL_PARK_WEST_N_7","street":"WEST 70TH STREET","from":"COLUMBUS AVENUE","to":"CENTRAL PARK WEST","side":"N","line":[[40.775022,-73.977236],[40.774968,-73.97711]],"rules":[{"category":"ASP_MON_THU","description":"NO PARKING (SANITATION BROOM SYMBOL) MONDAY THURSDAY 9AM-10:30AM <-> (SUPERSEDES SP-413C)","days":[1,4],"timeRanges":[{"start":540,"end":630}],"anytime":false,"arrow":"both"}],"dominantCategory":"ASP_MON_THU"},{"id":"WEST_70TH_STREET_COLUMBUS_AVENUE_CENTRAL_PARK_WEST_S_6","street":"WEST 70TH STREET","from":"COLUMBUS AVENUE","to":"CENTRAL PARK WEST","side":"S","line":[[40.775122,-73.977327],[40.775069,-73.9772]],"rules":[{"category":"ASP_TUE_FRI","description":"NO PARKING (SANITATION BROOM SYMBOL) TUESDAY FRIDAY 9AM-10:30AM --> (SUPERSEDES SP-415CA)","days":[2,5],"timeRanges":[{"start":540,"end":630}],"anytime":false,"arrow":"towards"},{"category":"NO_PARKING","description":"NO PARKING ANYTIME --> (SUPERSEDES SP-854CA)","days":[0,1,2,3,4,5,6],"timeRanges":[],"anytime":true,"arrow":"towards"}],"dominantCategory":"NO_PARKING"},{"id":"WEST_69TH_STREET_CENTRAL_PARK_WEST_COLUMBUS_AVENUE_N_0","street":"WEST 69TH STREET","from":"CENTRAL PARK WEST","to":"COLUMBUS AVENUE","side":"N","line":[[40.774381,-73.977514],[40.774492,-73.97778]],"rules":[{"category":"ASP_MON_THU","description":"NO PARKING (SANITATION BROOM SYMBOL) 8-9:30AM MON & THURS <----> (SUPERSEDED BY PS-54B)","days":[1,2,3,4,5,6],"timeRanges":[],"anytime":false,"arrow":"towards"}],"dominantCategory":"ASP_MON_THU"},{"id":"WEST_69TH_STREET_CENTRAL_PARK_WEST_COLUMBUS_AVENUE_N_1","street":"WEST 69TH STREET","from":"CENTRAL PARK WEST","to":"COLUMBUS AVENUE","side":"N","line":[[40.774492,-73.97778],[40.774653,-73.978166]],"rules":[{"category":"ASP_MON_THU","description":"NO PARKING (SANITATION BROOM SYMBOL) 8-9:30AM MON & THURS <----> (SUPERSEDED BY PS-54B)","days":[1,2,3,4,5,6],"timeRanges":[],"anytime":false,"arrow":"towards"}],"dominantCategory":"ASP_MON_THU"},{"id":"WEST_69TH_STREET_CENTRAL_PARK_WEST_COLUMBUS_AVENUE_N_2","street":"WEST 69TH STREET","from":"CENTRAL PARK WEST","to":"COLUMBUS AVENUE","side":"N","line":[[40.774653,-73.978166],[40.774768,-73.978442]],"rules":[{"category":"ASP_MON_THU","description":"NO PARKING (SANITATION BROOM SYMBOL) 8-9:30AM MON & THURS <----> (SUPERSEDED BY PS-54B)","days":[1,2,3,4,5,6],"timeRanges":[],"anytime":false,"arrow":"towards"}],"dominantCategory":"ASP_MON_THU"},{"id":"WEST_69TH_STREET_CENTRAL_PARK_WEST_COLUMBUS_AVENUE_N_3","street":"WEST 69TH STREET","from":"CENTRAL PARK WEST","to":"COLUMBUS AVENUE","side":"N","line":[[40.774768,-73.978442],[40.774864,-73.978673]],"rules":[{"category":"ASP_MON_THU","description":"NO PARKING (SANITATION BROOM SYMBOL) 8-9:30AM MON & THURS <----> (SUPERSEDED BY PS-54B)","days":[1,2,3,4,5,6],"timeRanges":[],"anytime":false,"arrow":"towards"}],"dominantCategory":"ASP_MON_THU"},{"id":"WEST_69TH_STREET_CENTRAL_PARK_WEST_COLUMBUS_AVENUE_N_4","street":"WEST 69TH STREET","from":"CENTRAL PARK WEST","to":"COLUMBUS AVENUE","side":"N","line":[[40.774864,-73.978673],[40.774999,-73.978996]],"rules":[{"category":"ASP_MON_THU","description":"NO PARKING (SANITATION BROOM SYMBOL) 8-9:30AM MON & THURS <----> (SUPERSEDED BY PS-54B)","days":[1,2,3,4,5,6],"timeRanges":[],"anytime":false,"arrow":"towards"}],"dominantCategory":"ASP_MON_THU"},{"id":"CENTRAL_PARK_WEST_WEST_70TH_STREET_WEST_69TH_STREET_W_0","street":"CENTRAL PARK WEST","from":"WEST 70TH STREET","to":"WEST 69TH STREET","side":"W","line":[[40.774257,-73.977348],[40.774317,-73.977307],[40.774478,-73.977193]],"rules":[{"category":"NO_STANDING","description":"BUS STOP SIGN (BUS & HANDICAP SYMBOLS) NO STANDING W/ SINGLE ARROW","days":[1,2,3,4,5,6],"timeRanges":[],"anytime":false,"arrow":null}],"dominantCategory":"NO_STANDING"},{"id":"CENTRAL_PARK_WEST_WEST_70TH_STREET_WEST_69TH_STREET_W_1","street":"CENTRAL PARK WEST","from":"WEST 70TH STREET","to":"WEST 69TH STREET","side":"W","line":[[40.774478,-73.977193],[40.774628,-73.977086],[40.774642,-73.977075]],"rules":[{"category":"NO_STANDING","description":"BUS STOP SIGN (BUS & HANDICAP SYMBOLS) NO STANDING W/ SINGLE ARROW","days":[1,2,3,4,5,6],"timeRanges":[],"anytime":false,"arrow":null},{"category":"ASP_MON_THU","description":"NO PARKING (SANITATION BROOM SYMBOL) MONDAY THURSDAY 8AM-9:30AM <-> (SUPERSEDES SP-412C)","days":[1,4],"timeRanges":[{"start":480,"end":570}],"anytime":false,"arrow":"both"}],"dominantCategory":"NO_STANDING"},{"id":"CENTRAL_PARK_WEST_WEST_68TH_STREET_WEST_67TH_STREET_W_0","street":"CENTRAL PARK WEST","from":"WEST 68TH STREET","to":"WEST 67TH STREET","side":"W","line":[[40.773696,-73.977847],[40.773449,-73.977964]],"rules":[{"category":"NO_STANDING","description":"BUS STOP SIGN (BUS & HANDICAP SYMBOLS) NO STANDING W/ SINGLE ARROW","days":[1,2,3,4,5,6],"timeRanges":[],"anytime":false,"arrow":null}],"dominantCategory":"NO_STANDING"},{"id":"CENTRAL_PARK_WEST_WEST_68TH_STREET_WEST_67TH_STREET_W_1","street":"CENTRAL PARK WEST","from":"WEST 68TH STREET","to":"WEST 67TH STREET","side":"W","line":[[40.773449,-73.977964],[40.773137,-73.97811]],"rules":[{"category":"NO_STANDING","description":"BUS STOP SIGN (BUS & HANDICAP SYMBOLS) NO STANDING W/ SINGLE ARROW","days":[1,2,3,4,5,6],"timeRanges":[],"anytime":false,"arrow":null}],"dominantCategory":"NO_STANDING"},{"id":"CENTRAL_PARK_WEST_WEST_68TH_STREET_WEST_67TH_STREET_W_2","street":"CENTRAL PARK WEST","from":"WEST 68TH STREET","to":"WEST 67TH STREET","side":"W","line":[[40.773137,-73.97811],[40.773033,-73.978159]],"rules":[{"category":"NO_PARKING","description":"NO PARKING MONDAY-FRIDAY 7AM-7PM --> (SUPERSEDES R7-43RA)","days":[1,2,3,4,5],"timeRanges":[{"start":420,"end":1140}],"anytime":false,"arrow":"towards"}],"dominantCategory":"NO_PARKING"},{"id":"CENTRAL_PARK_WEST_WEST_67TH_STREET_WEST_66TH_STREET_W_0","street":"CENTRAL PARK WEST","from":"WEST 67TH STREET","to":"WEST 66TH STREET","side":"W","line":[[40.773008,-73.978179],[40.772854,-73.978335]],"rules":[{"category":"ASP_MON_THU","description":"NO PARKING (SANITATION BROOM SYMBOL) MONDAY THURSDAY 8AM-9:30AM <-> (SUPERSEDES SP-412C)","days":[1,4],"timeRanges":[{"start":480,"end":570}],"anytime":false,"arrow":"both"}],"dominantCategory":"ASP_MON_THU"},{"id":"WEST_68TH_STREET_COLUMBUS_AVENUE_CENTRAL_PARK_WEST_N_4","street":"WEST 68TH STREET","from":"COLUMBUS AVENUE","to":"CENTRAL PARK WEST","side":"N","line":[[40.774269,-73.97936],[40.77405,-73.978842]],"rules":[{"category":"ASP_MON_THU","description":"NO PARKING (SANITATION BROOM SYMBOL) MONDAY THURSDAY 8AM-9:30AM <-> (SUPERSEDES SP-412C)","days":[1,4],"timeRanges":[{"start":480,"end":570}],"anytime":false,"arrow":"both"},{"category":"ASP_MON_THU","description":"NO PARKING (SANITATION BROOM SYMBOL) MONDAY THURSDAY 8AM-9:30AM <-> (SUPERSEDES SP-412C)","days":[1,4],"timeRanges":[{"start":480,"end":570}],"anytime":false,"arrow":"both"}],"dominantCategory":"ASP_MON_THU"},{"id":"WEST_68TH_STREET_COLUMBUS_AVENUE_CENTRAL_PARK_WEST_N_5","street":"WEST 68TH STREET","from":"COLUMBUS AVENUE","to":"CENTRAL PARK WEST","side":"N","line":[[40.77405,-73.978842],[40.773924,-73.978547],[40.773892,-73.97847]],"rules":[{"category":"ASP_MON_THU","description":"NO PARKING (SANITATION BROOM SYMBOL) MONDAY THURSDAY 8AM-9:30AM <-> (SUPERSEDES SP-412C)","days":[1,4],"timeRanges":[{"start":480,"end":570}],"anytime":false,"arrow":"both"},{"category":"ASP_MON_THU","description":"NO PARKING (SANITATION BROOM SYMBOL) MONDAY THURSDAY 8AM-9:30AM <-> (SUPERSEDES SP-412C)","days":[1,4],"timeRanges":[{"start":480,"end":570}],"anytime":false,"arrow":"both"}],"dominantCategory":"ASP_MON_THU"},{"id":"WEST_68TH_STREET_COLUMBUS_AVENUE_CENTRAL_PARK_WEST_N_6","street":"WEST 68TH STREET","from":"COLUMBUS AVENUE","to":"CENTRAL PARK WEST","side":"N","line":[[40.773892,-73.97847],[40.773783,-73.978207]],"rules":[{"category":"ASP_MON_THU","description":"NO PARKING (SANITATION BROOM SYMBOL) MONDAY THURSDAY 8AM-9:30AM <-> (SUPERSEDES SP-412C)","days":[1,4],"timeRanges":[{"start":480,"end":570}],"anytime":false,"arrow":"both"},{"category":"ASP_MON_THU","description":"NO PARKING (SANITATION BROOM SYMBOL) MONDAY THURSDAY 8AM-9:30AM <-> (SUPERSEDES SP-412C)","days":[1,4],"timeRanges":[{"start":480,"end":570}],"anytime":false,"arrow":"both"}],"dominantCategory":"ASP_MON_THU"},{"id":"WEST_68TH_STREET_COLUMBUS_AVENUE_CENTRAL_PARK_WEST_N_7","street":"WEST 68TH STREET","from":"COLUMBUS AVENUE","to":"CENTRAL PARK WEST","side":"N","line":[[40.773783,-73.978207],[40.77373,-73.978081]],"rules":[{"category":"ASP_MON_THU","description":"NO PARKING (SANITATION BROOM SYMBOL) MONDAY THURSDAY 8AM-9:30AM <-> (SUPERSEDES SP-412C)","days":[1,4],"timeRanges":[{"start":480,"end":570}],"anytime":false,"arrow":"both"}],"dominantCategory":"ASP_MON_THU"},{"id":"CENTRAL_PARK_WEST_WEST_66TH_STREET_WEST_67TH_STREET_E_1","street":"CENTRAL PARK WEST","from":"WEST 66TH STREET","to":"WEST 67TH STREET","side":"E","line":[[40.772796,-73.978394],[40.772883,-73.978306]],"rules":[{"category":"NO_STANDING","description":"BUS STOP SIGN (BUS & HANDICAP SYMBOLS) NO STANDING W/ SINGLE ARROW","days":[1,2,3,4,5,6],"timeRanges":[],"anytime":false,"arrow":null}],"dominantCategory":"NO_STANDING"},{"id":"CENTRAL_PARK_WEST_WEST_69TH_STREET_WEST_68TH_STREET_W_0","street":"CENTRAL PARK WEST","from":"WEST 69TH STREET","to":"WEST 68TH STREET","side":"W","line":[[40.773627,-73.977808],[40.773687,-73.977767],[40.7739,-73.977612]],"rules":[{"category":"ASP_MON_THU","description":"NO PARKING (SANITATION BROOM SYMBOL) MONDAY THURSDAY 8AM-9:30AM <-> (SUPERSEDES SP-412C)","days":[1,4],"timeRanges":[{"start":480,"end":570}],"anytime":false,"arrow":"both"}],"dominantCategory":"ASP_MON_THU"},{"id":"CENTRAL_PARK_WEST_WEST_69TH_STREET_WEST_68TH_STREET_W_1","street":"CENTRAL PARK WEST","from":"WEST 69TH STREET","to":"WEST 68TH STREET","side":"W","line":[[40.7739,-73.977612],[40.774156,-73.977424]],"rules":[{"category":"ASP_MON_THU","description":"NO PARKING (SANITATION BROOM SYMBOL) MONDAY THURSDAY 8AM-9:30AM <-> (SUPERSEDES SP-412C)","days":[1,4],"timeRanges":[{"start":480,"end":570}],"anytime":false,"arrow":"both"},{"category":"ASP_MON_THU","description":"NO PARKING (SANITATION BROOM SYMBOL) MONDAY THURSDAY 8AM-9:30AM <-> (SUPERSEDES SP-412C)","days":[1,4],"timeRanges":[{"start":480,"end":570}],"anytime":false,"arrow":"both"}],"dominantCategory":"ASP_MON_THU"},{"id":"CENTRAL_PARK_WEST_WEST_69TH_STREET_WEST_68TH_STREET_W_2","street":"CENTRAL PARK WEST","from":"WEST 69TH STREET","to":"WEST 68TH STREET","side":"W","line":[[40.774156,-73.977424],[40.774208,-73.977386],[40.774252,-73.977351]],"rules":[{"category":"ASP_MON_THU","description":"NO PARKING (SANITATION BROOM SYMBOL) MONDAY THURSDAY 8AM-9:30AM <-> (SUPERSEDES SP-412C)","days":[1,4],"timeRanges":[{"start":480,"end":570}],"anytime":false,"arrow":"both"}],"dominantCategory":"ASP_MON_THU"},{"id":"WEST_67TH_STREET_CENTRAL_PARK_WEST_COLUMBUS_AVENUE_S_0","street":"WEST 67TH STREET","from":"CENTRAL PARK WEST","to":"COLUMBUS AVENUE","side":"S","line":[[40.772964,-73.978187],[40.773024,-73.978327],[40.773041,-73.978365]],"rules":[{"category":"ASP_TUE_FRI","description":"NO PARKING (SANITATION BROOM SYMBOL) TUESDAY FRIDAY 8AM-9:30AM <-> (SUPERSEDES SP-844C)","days":[2,5],"timeRanges":[{"start":480,"end":570}],"anytime":false,"arrow":"both"}],"dominantCategory":"ASP_TUE_FRI"},{"id":"WEST_67TH_STREET_CENTRAL_PARK_WEST_COLUMBUS_AVENUE_S_1","street":"WEST 67TH STREET","from":"CENTRAL PARK WEST","to":"COLUMBUS AVENUE","side":"S","line":[[40.773041,-73.978365],[40.773074,-73.978437],[40.773185,-73.978708]],"rules":[{"category":"ASP_TUE_FRI","description":"NO PARKING (SANITATION BROOM SYMBOL) TUESDAY FRIDAY 8AM-9:30AM <-> (SUPERSEDES SP-844C)","days":[2,5],"timeRanges":[{"start":480,"end":570}],"anytime":false,"arrow":"both"},{"category":"ASP_TUE_FRI","description":"NO PARKING (SANITATION BROOM SYMBOL) TUESDAY FRIDAY 8AM-9:30AM <-> (SUPERSEDES SP-844C)","days":[2,5],"timeRanges":[{"start":480,"end":570}],"anytime":false,"arrow":"both"}],"dominantCategory":"ASP_TUE_FRI"},{"id":"WEST_67TH_STREET_CENTRAL_PARK_WEST_COLUMBUS_AVENUE_S_2","street":"WEST 67TH STREET","from":"CENTRAL PARK WEST","to":"COLUMBUS AVENUE","side":"S","line":[[40.773185,-73.978708],[40.773317,-73.979033]],"rules":[{"category":"ASP_TUE_FRI","description":"NO PARKING (SANITATION BROOM SYMBOL) TUESDAY FRIDAY 8AM-9:30AM <-> (SUPERSEDES SP-844C)","days":[2,5],"timeRanges":[{"start":480,"end":570}],"anytime":false,"arrow":"both"},{"category":"ASP_TUE_FRI","description":"NO PARKING (SANITATION BROOM SYMBOL) TUESDAY FRIDAY 8AM-9:30AM <-> (SUPERSEDES SP-844C)","days":[2,5],"timeRanges":[{"start":480,"end":570}],"anytime":false,"arrow":"both"}],"dominantCategory":"ASP_TUE_FRI"},{"id":"WEST_67TH_STREET_CENTRAL_PARK_WEST_COLUMBUS_AVENUE_S_3","street":"WEST 67TH STREET","from":"CENTRAL PARK WEST","to":"COLUMBUS AVENUE","side":"S","line":[[40.773317,-73.979033],[40.773425,-73.979297],[40.773705,-73.979959]],"rules":[{"category":"ASP_TUE_FRI","description":"NO PARKING (SANITATION BROOM SYMBOL) TUESDAY FRIDAY 8AM-9:30AM <-> (SUPERSEDES SP-844C)","days":[2,5],"timeRanges":[{"start":480,"end":570}],"anytime":false,"arrow":"both"},{"category":"ASP_TUE_FRI","description":"NO PARKING (SANITATION BROOM SYMBOL) TUESDAY FRIDAY 8AM-9:30AM <-> (SUPERSEDES SP-844C)","days":[2,5],"timeRanges":[{"start":480,"end":570}],"anytime":false,"arrow":"both"}],"dominantCategory":"ASP_TUE_FRI"}]