[{"id":"ORCHARD_STREET_CANAL_STREET_HESTER_STREET_E_4","street":"ORCHARD STREET","from":"CANAL STREET","to":"HESTER STREET","side":"E","line":[[40.715878,-73.991352],[40.71598,-73.9913],[40.71603,-73.99127],[40.71603,-73.99127]],"rules":[{"category":"METERED","description":"2 HMP SATURDAY 9AM-7PM <->","days":[6],"timeRanges":[{"start":540,"end":1140}],"anytime":false,"arrow":"both"},{"category":"ASP_OVERNIGHT_TTHS","description":"NO PARKING (SANITATION BROOM SYMBOL) MOON & STARS (SYMBOLS) TUESDAY THURSDAY SATURDAY MIDNIGHT-3AM <-> (SUPERSEDES SP-339C)","days":[2,4,6],"timeRanges":[{"start":0,"end":180}],"anytime":false,"arrow":"both"},{"category":"NO_PARKING","description":"NO PARKING MONDAY-FRIDAY 7AM-7PM <-> (SUPERSEDES R7-43R)","days":[1,2,3,4,5],"timeRanges":[{"start":420,"end":1140}],"anytime":false,"arrow":"both"}],"dominantCategory":"NO_PARKING"},{"id":"HESTER_STREET_ORCHARD_STREET_LUDLOW_STREET_N_0","street":"HESTER STREET","from":"ORCHARD STREET","to":"LUDLOW STREET","side":"N","line":[[40.71607,-73.99131],[40.71605,-73.99124],[40.716028,-73.991169]],"rules":[{"category":"ASP_DAILY","description":"NO PARKING (SANITATION BROOM SYMBOL) W/ (MOON/STARS SYMBOLS) MONDAY WEDNESDAY FRIDAY 3AM-6AM <-> (SUPERSEDES SP-342C)","days":[1,3,5],"timeRanges":[{"start":180,"end":360}],"anytime":false,"arrow":"both"},{"category":"SPECIAL","description":"STAR (SYMBOL) AVO DEPT OF EDUCATION SCHOOL DAYS 7AM-4PM <-> (SUPERSEDES PS-16E) (PUBLIC SCHOOL SIGN)","days":[1,2,3,4,5,6],"timeRanges":[{"start":420,"end":960}],"anytime":false,"arrow":"both"}],"dominantCategory":"SPECIAL"},{"id":"HESTER_STREET_ORCHARD_STREET_LUDLOW_STREET_N_1","street":"HESTER STREET","from":"ORCHARD STREET","to":"LUDLOW STREET","side":"N","line":[[40.716028,-73.991169],[40.715973,-73.990988]],"rules":[{"category":"ASP_DAILY","description":"NO PARKING (SANITATION BROOM SYMBOL) W/ (MOON/STARS SYMBOLS) MONDAY WEDNESDAY FRIDAY 3AM-6AM <-> (SUPERSEDES SP-342C)","days":[1,3,5],"timeRanges":[{"start":180,"end":360}],"anytime":false,"arrow":"both"},{"category":"SPECIAL","description":"STAR (SYMBOL) AVO DEPT OF EDUCATION SCHOOL DAYS 7AM-4PM <-> (SUPERSEDES PS-16E) (PUBLIC SCHOOL SIGN)","days":[1,2,3,4,5,6],"timeRanges":[{"start":420,"end":960}],"anytime":false,"arrow":"both"},{"category":"ASP_DAILY","description":"NO PARKING (SANITATION BROOM SYMBOL) W/ (MOON/STARS SYMBOLS) MONDAY WEDNESDAY FRIDAY 3AM-6AM <-> (SUPERSEDES SP-342C)","days":[1,3,5],"timeRanges":[{"start":180,"end":360}],"anytime":false,"arrow":"both"}],"dominantCategory":"SPECIAL"},{"id":"HESTER_STREET_ORCHARD_STREET_LUDLOW_STREET_N_2","street":"HESTER STREET","from":"ORCHARD STREET","to":"LUDLOW STREET","side":"N","line":[[40.715973,-73.990988],[40.715938,-73.990874]],"rules":[{"category":"SPECIAL","description":"STAR (SYMBOL) AVO DEPT OF EDUCATION SCHOOL DAYS 7AM-4PM --> (SUPERSEDES PS-16EA)(PUBLIC SCHOOL SIGN)","days":[1,2,3,4,5,6],"timeRanges":[{"start":420,"end":960}],"anytime":false,"arrow":"towards"},{"category":"ASP_DAILY","description":"NO PARKING (SANITATION BROOM SYMBOL) W/ (MOON/STARS SYMBOLS) MONDAY WEDNESDAY FRIDAY 3AM-6AM <-> (SUPERSEDES SP-342C)","days":[1,3,5],"timeRanges":[{"start":180,"end":360}],"anytime":false,"arrow":"both"},{"category":"ASP_DAILY","description":"NO PARKING (SANITATION BROOM SYMBOL) W/ (MOON/STARS SYMBOLS) MONDAY WEDNESDAY FRIDAY 3AM-6AM <-> (SUPERSEDES SP-342C)","days":[1,3,5],"timeRanges":[{"start":180,"end":360}],"anytime":false,"arrow":"both"}],"dominantCategory":"SPECIAL"},{"id":"ELDRIDGE_STREET_CANAL_STREET_HESTER_STREET_E_6","street":"ELDRIDGE STREET","from":"CANAL STREET","to":"HESTER STREET","side":"E","line":[[40.716239,-73.992913],[40.716308,-73.992877]],"rules":[{"category":"NO_PARKING","description":"NO PARKING ANYTIME --> (SUPERSEDES SP-854CA)","days":[0,1,2,3,4,5,6],"timeRanges":[],"anytime":true,"arrow":"towards"}],"dominantCategory":"NO_PARKING"},{"id":"ELDRIDGE_STREET_CANAL_STREET_HESTER_STREET_E_7","street":"ELDRIDGE STREET","from":"CANAL STREET","to":"HESTER STREET","side":"E","line":[[40.716308,-73.992877],[40.71644,-73.99281],[40.71649,-73.99278],[40.71649,-73.99278]],"rules":[{"category":"ASP_DAILY","description":"NO PARKING (SANITATION BROOM SYMBOL) 8:30AM-9AM EXCEPT SUNDAY --> (SUPERSEDES SP-855CA)","days":[1,2,3,4,5,6],"timeRanges":[{"start":510,"end":540}],"anytime":false,"arrow":"towards"}],"dominantCategory":"ASP_DAILY"},{"id":"ORCHARD_STREET_CANAL_STREET_HESTER_STREET_W_4","street":"ORCHARD STREET","from":"CANAL STREET","to":"HESTER STREET","side":"W","line":[[40.715843,-73.99145],[40.71598,-73.99138],[40.71603,-73.99135],[40.71603,-73.99135]],"rules":[{"category":"ASP_OVERNIGHT_MWF","description":"NO PARKING (SANITATION BROOM SYMBOL) MOON & STARS (SYMBOLS) MONDAY WEDNESDAY FRIDAY MIDNIGHT-3AM <-> (SUPERSEDES SP-702C)","days":[1,3,5],"timeRanges":[{"start":0,"end":180}],"anytime":false,"arrow":"both"},{"category":"METERED","description":"2 HMP 9AM-7PM EXCEPT SUNDAY <-> (SUPERSEDES R7-182RB)","days":[1,2,3,4,5,6],"timeRanges":[{"start":540,"end":1140}],"anytime":false,"arrow":"both"}],"dominantCategory":"METERED"},{"id":"HESTER_STREET_ORCHARD_STREET_LUDLOW_STREET_S_0","street":"HESTER STREET","from":"ORCHARD STREET","to":"LUDLOW STREET","side":"S","line":[[40.71599,-73.99131],[40.71597,-73.99124],[40.715936,-73.991129]],"rules":[{"category":"SPECIAL","description":"STAR (SYMBOL) AVO DEPT OF EDUCATION SCHOOL DAYS 7AM-4PM <-> (SUPERSEDES PS-16E) (PUBLIC SCHOOL SIGN)","days":[1,2,3,4,5,6],"timeRanges":[{"start":420,"end":960}],"anytime":false,"arrow":"both"},{"category":"ASP_DAILY","description":"NO PARKING (SANITATION BROOM SYMBOL) MOON & STARS (SYMBOLS) TUESDAY THURSDAY SATURDAY 3AM-6AM <-> (SUPERSEDES SP-343C)","days":[2,4,6],"timeRanges":[{"start":180,"end":360}],"anytime":false,"arrow":"both"}],"dominantCategory":"SPECIAL"},{"id":"ALLEN_STREET_GRAND_STREET_BROOME_STREET_E_0","street":"ALLEN STREET","from":"GRAND STREET","to":"BROOME STREET","side":"E","line":[[40.71738,-73.99123],[40.71743,-73.99121],[40.71745,-73.9912],[40.7175,-73.99117],[40.71755,-73.99112],[40.717604,-73.991093]],"rules":[{"category":"NO_STANDING","description":"BUS STOP SIGN (BUS & HANDICAP SYMBOLS) NO STANDING W/ SINGLE ARROW","days":[1,2,3,4,5,6],"timeRanges":[],"anytime":false,"arrow":null}],"dominantCategory":"NO_STANDING"},{"id":"ALLEN_STREET_GRAND_STREET_BROOME_STREET_E_1","street":"ALLEN STREET","from":"GRAND STREET","to":"BROOME STREET","side":"E","line":[[40.717604,-73.991093],[40.71761,-73.99109],[40.717867,-73.990959]],"rules":[{"category":"NO_STANDING","description":"BUS STOP SIGN (BUS & HANDICAP SYMBOLS) NO STANDING W/ SINGLE ARROW","days":[1,2,3,4,5,6],"timeRanges":[],"anytime":false,"arrow":null},{"category":"METERED","description":"2 HMP 9AM-7PM EXCEPT SUNDAY <-> (SUPERSEDES R7-182RB)","days":[1,2,3,4,5,6],"timeRanges":[{"start":540,"end":1140}],"anytime":false,"arrow":"both"},{"category":"ASP_OVERNIGHT_TTHS","description":"NO PARKING (SANITATION BROOM SYMBOL) MOON & STARS (SYMBOLS) TUESDAY THURSDAY SATURDAY MIDNIGHT-3AM <-> (SUPERSEDES SP-339C)","days":[2,4,6],"timeRanges":[{"start":0,"end":180}],"anytime":false,"arrow":"both"}],"dominantCategory":"NO_STANDING"},{"id":"ALLEN_STREET_GRAND_STREET_BROOME_STREET_E_2","street":"ALLEN STREET","from":"GRAND STREET","to":"BROOME STREET","side":"E","line":[[40.717867,-73.990959],[40.718033,-73.990874]],"rules":[{"category":"METERED","description":"2 HMP 9AM-7PM EXCEPT SUNDAY <-> (SUPERSEDES R7-182RB)","days":[1,2,3,4,5,6],"timeRanges":[{"start":540,"end":1140}],"anytime":false,"arrow":"both"},{"category":"ASP_OVERNIGHT_TTHS","description":"NO PARKING (SANITATION BROOM SYMBOL) MOON & STARS (SYMBOLS) TUESDAY THURSDAY SATURDAY MIDNIGHT-3AM <-> (SUPERSEDES SP-339C)","days":[2,4,6],"timeRanges":[{"start":0,"end":180}],"anytime":false,"arrow":"both"}],"dominantCategory":"METERED"},{"id":"ELDRIDGE_STREET_GRAND_STREET_BROOME_STREET_E_0","street":"ELDRIDGE STREET","from":"GRAND STREET","to":"BROOME STREET","side":"E","line":[[40.71767,-73.99218],[40.71774,-73.99214],[40.717876,-73.99207]],"rules":[{"category":"METERED","description":"2 HMP 9AM-7PM EXCEPT SUNDAY <-> (SUPERSEDES R7-182RB)","days":[1,2,3,4,5,6],"timeRanges":[{"start":540,"end":1140}],"anytime":false,"arrow":"both"},{"category":"ASP_DAILY","description":"NO PARKING (SANITATION BROOM SYMBOL) 8:30AM-9AM EXCEPT SUNDAY <-> (SUPERSEDES SP-855C)","days":[1,2,3,4,5,6],"timeRanges":[{"start":510,"end":540}],"anytime":false,"arrow":"both"}],"dominantCategory":"METERED"},{"id":"ELDRIDGE_STREET_GRAND_STREET_BROOME_STREET_E_1","street":"ELDRIDGE STREET","from":"GRAND STREET","to":"BROOME STREET","side":"E","line":[[40.717876,-73.99207],[40.718062,-73.991975]],"rules":[{"category":"METERED","description":"2 HMP 9AM-7PM EXCEPT SUNDAY <-> (SUPERSEDES R7-182RB)","days":[1,2,3,4,5,6],"timeRanges":[{"start":540,"end":1140}],"anytime":false,"arrow":"both"},{"category":"ASP_DAILY","description":"NO PARKING (SANITATION BROOM SYMBOL) 8:30AM-9AM EXCEPT SUNDAY <-> (SUPERSEDES SP-855C)","days":[1,2,3,4,5,6],"timeRanges":[{"start":510,"end":540}],"anytime":false,"arrow":"both"},{"category":"ASP_DAILY","description":"NO PARKING (SANITATION BROOM SYMBOL) 8:30AM-9AM EXCEPT SUNDAY <-> (SUPERSEDES SP-855C)","days":[1,2,3,4,5,6],"timeRanges":[{"start":510,"end":540}],"anytime":false,"arrow":"both"},{"category":"METERED","description":"2 HMP 9AM-7PM EXCEPT SUNDAY <-> (SUPERSEDES R7-182RB)","days":[1,2,3,4,5,6],"timeRanges":[{"start":540,"end":1140}],"anytime":false,"arrow":"both"}],"dominantCategory":"METERED"},{"id":"HESTER_STREET_ELDRIDGE_STREET_ALLEN_STREET_S_0","street":"HESTER STREET","from":"ELDRIDGE STREET","to":"ALLEN STREET","side":"S","line":[[40.716271,-73.992233],[40.716359,-73.992525]],"rules":[{"category":"NO_STANDING","description":"NO STANDING FIRE ZONE --> (SUPERSEDES SP-453BA)","days":[1,2,3,4,5,6],"timeRanges":[],"anytime":false,"arrow":"towards"},{"category":"ASP_DAILY","description":"NO PARKING (SANITATION BROOM SYMBOL) MOON & STARS (SYMBOLS) TUESDAY THURSDAY SATURDAY 3AM-6AM <-> (SUPERSEDES SP-343C)","days":[2,4,6],"timeRanges":[{"start":180,"end":360}],"anytime":false,"arrow":"both"},{"category":"METERED","description":"2 HMP 9AM-7PM EXCEPT SUNDAY <-> (SUPERSEDES R7-182RB)","days":[1,2,3,4,5,6],"timeRanges":[{"start":540,"end":1140}],"anytime":false,"arrow":"both"}],"dominantCategory":"NO_STANDING"},{"id":"HESTER_STREET_ELDRIDGE_STREET_ALLEN_STREET_S_1","street":"HESTER STREET","from":"ELDRIDGE STREET","to":"ALLEN STREET","side":"S","line":[[40.716359,-73.992525],[40.71643,-73.99276],[40.71645,-73.99282],[40.71645,-73.99282]],"rules":[{"category":"ASP_DAILY","description":"NO PARKING (SANITATION BROOM SYMBOL) MOON & STARS (SYMBOLS) TUESDAY THURSDAY SATURDAY 3AM-6AM <-> (SUPERSEDES SP-343C)","days":[2,4,6],"timeRanges":[{"start":180,"end":360}],"anytime":false,"arrow":"both"},{"category":"METERED","description":"2 HMP 9AM-7PM EXCEPT SUNDAY <-> (SUPERSEDES R7-182RB)","days":[1,2,3,4,5,6],"timeRanges":[{"start":540,"end":1140}],"anytime":false,"arrow":"both"}],"dominantCategory":"METERED"},{"id":"ORCHARD_STREET_HESTER_STREET_GRAND_STREET_W_0","street":"ORCHARD STREET","from":"HESTER STREET","to":"GRAND STREET","side":"W","line":[[40.71603,-73.99135],[40.71608,-73.99133],[40.716136,-73.991301]],"rules":[{"category":"METERED","description":"2 HMP 9AM-7PM EXCEPT SUNDAY <-> (SUPERSEDES R7-182RB)","days":[1,2,3,4,5,6],"timeRanges":[{"start":540,"end":1140}],"anytime":false,"arrow":"both"},{"category":"ASP_OVERNIGHT_MWF","description":"NO PARKING (SANITATION BROOM SYMBOL) MOON & STARS (SYMBOLS) MONDAY WEDNESDAY FRIDAY MIDNIGHT-3AM <-> (SUPERSEDES SP-702C)","days":[1,3,5],"timeRanges":[{"start":0,"end":180}],"anytime":false,"arrow":"both"}],"dominantCategory":"METERED"},{"id":"ORCHARD_STREET_HESTER_STREET_GRAND_STREET_W_1","street":"ORCHARD STREET","from":"HESTER STREET","to":"GRAND STREET","side":"W","line":[[40.716136,-73.991301],[40.716382,-73.99117]],"rules":[{"category":"METERED","description":"2 HMP 9AM-7PM EXCEPT SUNDAY <-> (SUPERSEDES R7-182RB)","days":[1,2,3,4,5,6],"timeRanges":[{"start":540,"end":1140}],"anytime":false,"arrow":"both"},{"category":"ASP_OVERNIGHT_MWF","description":"NO PARKING (SANITATION BROOM SYMBOL) MOON & STARS (SYMBOLS) MONDAY WEDNESDAY FRIDAY MIDNIGHT-3AM <-> (SUPERSEDES SP-702C)","days":[1,3,5],"timeRanges":[{"start":0,"end":180}],"anytime":false,"arrow":"both"},{"category":"ASP_OVERNIGHT_MWF","description":"NO PARKING (SANITATION BROOM SYMBOL) MOON & STARS (SYMBOLS) MONDAY WEDNESDAY FRIDAY MIDNIGHT-3AM <-> (SUPERSEDES SP-702C)","days":[1,3,5],"timeRanges":[{"start":0,"end":180}],"anytime":false,"arrow":"both"},{"category":"METERED","description":"2 HMP 9AM-7PM EXCEPT SUNDAY <-> (SUPERSEDES R7-182RB)","days":[1,2,3,4,5,6],"timeRanges":[{"start":540,"end":1140}],"anytime":false,"arrow":"both"}],"dominantCategory":"METERED"},{"id":"ORCHARD_STREET_HESTER_STREET_GRAND_STREET_W_2","street":"ORCHARD STREET","from":"HESTER STREET","to":"GRAND STREET","side":"W","line":[[40.716382,-73.99117],[40.71661,-73.99105],[40.716667,-73.99102]],"rules":[{"category":"ASP_OVERNIGHT_MWF","description":"NO PARKING (SANITATION BROOM SYMBOL) MOON & STARS (SYMBOLS) MONDAY WEDNESDAY FRIDAY MIDNIGHT-3AM <-> (SUPERSEDES SP-702C)","days":[1,3,5],"timeRanges":[{"start":0,"end":180}],"anytime":false,"arrow":"both"},{"category":"METERED","description":"2 HMP 9AM-7PM EXCEPT SUNDAY <-> (SUPERSEDES R7-182RB)","days":[1,2,3,4,5,6],"timeRanges":[{"start":540,"end":1140}],"anytime":false,"arrow":"both"},{"category":"ASP_OVERNIGHT_MWF","description":"NO PARKING (SANITATION BROOM SYMBOL) MOON & STARS (SYMBOLS) MONDAY WEDNESDAY FRIDAY MIDNIGHT-3AM <-> (SUPERSEDES SP-702C)","days":[1,3,5],"timeRanges":[{"start":0,"end":180}],"anytime":false,"arrow":"both"},{"category":"METERED","description":"2 HMP 9AM-7PM EXCEPT SUNDAY <-> (SUPERSEDES R7-182RB)","days":[1,2,3,4,5,6],"timeRanges":[{"start":540,"end":1140}],"anytime":false,"arrow":"both"}],"dominantCategory":"METERED"},{"id":"ORCHARD_STREET_HESTER_STREET_GRAND_STREET_W_3","street":"ORCHARD STREET","from":"HESTER STREET","to":"GRAND STREET","side":"W","line":[[40.716667,-73.99102],[40.716963,-73.990867]],"rules":[{"category":"ASP_OVERNIGHT_MWF","description":"NO PARKING (SANITATION BROOM SYMBOL) MOON & STARS (SYMBOLS) MONDAY WEDNESDAY FRIDAY MIDNIGHT-3AM <-> (SUPERSEDES SP-702C)","days":[1,3,5],"timeRanges":[{"start":0,"end":180}],"anytime":false,"arrow":"both"},{"category":"METERED","description":"2 HMP 9AM-7PM EXCEPT SUNDAY <-> (SUPERSEDES R7-182RB)","days":[1,2,3,4,5,6],"timeRanges":[{"start":540,"end":1140}],"anytime":false,"arrow":"both"},{"category":"ASP_OVERNIGHT_MWF","description":"NO PARKING (SANITATION BROOM SYMBOL) MOON & STARS (SYMBOLS) MONDAY WEDNESDAY FRIDAY MIDNIGHT-3AM <-> (SUPERSEDES SP-702C)","days":[1,3,5],"timeRanges":[{"start":0,"end":180}],"anytime":false,"arrow":"both"},{"category":"METERED","description":"2 HMP 9AM-7PM EXCEPT SUNDAY <-> (SUPERSEDES R7-182RB)","days":[1,2,3,4,5,6],"timeRanges":[{"start":540,"end":1140}],"anytime":false,"arrow":"both"}],"dominantCategory":"METERED"},{"id":"ORCHARD_STREET_HESTER_STREET_GRAND_STREET_W_4","street":"ORCHARD STREET","from":"HESTER STREET","to":"GRAND STREET","side":"W","line":[[40.716963,-73.990867],[40.71713,-73.99078],[40.71721,-73.99074],[40.71721,-73.99074]],"rules":[{"category":"ASP_OVERNIGHT_MWF","description":"NO PARKING (SANITATION BROOM SYMBOL) MOON & STARS (SYMBOLS) MONDAY WEDNESDAY FRIDAY MIDNIGHT-3AM <-> (SUPERSEDES SP-702C)","days":[1,3,5],"timeRanges":[{"start":0,"end":180}],"anytime":false,"arrow":"both"},{"category":"METERED","description":"2 HMP 9AM-7PM EXCEPT SUNDAY <-> (SUPERSEDES R7-182RB)","days":[1,2,3,4,5,6],"timeRanges":[{"start":540,"end":1140}],"anytime":false,"arrow":"both"}],"dominantCategory":"METERED"},{"id":"ELDRIDGE_STREET_HESTER_STREET_GRAND_STREET_W_0","street":"ELDRIDGE STREET","from":"HESTER STREET","to":"GRAND STREET","side":"W","line":[[40.71649,-73.99286],[40.71653,-73.99284],[40.716592,-73.992808]],"rules":[{"category":"NO_PARKING","description":"NO PARKING MONDAY-FRIDAY 7AM-7PM <-> (SUPERSEDES R7-43R)","days":[1,2,3,4,5],"timeRanges":[{"start":420,"end":1140}],"anytime":false,"arrow":"both"}],"dominantCategory":"NO_PARKING"},{"id":"ELDRIDGE_STREET_HESTER_STREET_GRAND_STREET_W_1","street":"ELDRIDGE STREET","from":"HESTER STREET","to":"GRAND STREET","side":"W","line":[[40.716592,-73.992808],[40.716781,-73.992712]],"rules":[{"category":"NO_PARKING","description":"NO PARKING MONDAY-FRIDAY 7AM-7PM <-> (SUPERSEDES R7-43R)","days":[1,2,3,4,5],"timeRanges":[{"start":420,"end":1140}],"anytime":false,"arrow":"both"},{"category":"NO_PARKING","description":"NO PARKING MONDAY-FRIDAY 7AM-7PM <-> (SUPERSEDES R7-43R)","days":[1,2,3,4,5],"timeRanges":[{"start":420,"end":1140}],"anytime":false,"arrow":"both"}],"dominantCategory":"NO_PARKING"},{"id":"ELDRIDGE_STREET_HESTER_STREET_GRAND_STREET_W_2","street":"ELDRIDGE STREET","from":"HESTER STREET","to":"GRAND STREET","side":"W","line":[[40.716781,-73.992712],[40.716909,-73.992647]],"rules":[{"category":"NO_PARKING","description":"NO PARKING MONDAY-FRIDAY 7AM-7PM <-> (SUPERSEDES R7-43R)","days":[1,2,3,4,5],"timeRanges":[{"start":420,"end":1140}],"anytime":false,"arrow":"both"}],"dominantCategory":"NO_PARKING"},{"id":"ELDRIDGE_STREET_HESTER_STREET_GRAND_STREET_W_3","street":"ELDRIDGE STREET","from":"HESTER STREET","to":"GRAND STREET","side":"W","line":[[40.716909,-73.992647],[40.716981,-73.99261]],"rules":[{"category":"NO_PARKING","description":"NO PARKING MONDAY-FRIDAY 7AM-7PM --> (SUPERSEDES R7-43RA)","days":[1,2,3,4,5],"timeRanges":[{"start":420,"end":1140}],"anytime":false,"arrow":"towards"}],"dominantCategory":"NO_PARKING"},{"id":"ELDRIDGE_STREET_HESTER_STREET_GRAND_STREET_W_4","street":"ELDRIDGE STREET","from":"HESTER STREET","to":"GRAND STREET","side":"W","line":[[40.716981,-73.99261],[40.717226,-73.992486]],"rules":[{"category":"NO_PARKING","description":"NO PARKING ANYTIME --> (SUPERSEDES SP-854CA)","days":[0,1,2,3,4,5,6],"timeRanges":[],"anytime":true,"arrow":"towards"},{"category":"NO_PARKING","description":"NO PARKING MONDAY-FRIDAY 7AM-7PM <-> (SUPERSEDES R7-43R)","days":[1,2,3,4,5],"timeRanges":[{"start":420,"end":1140}],"anytime":false,"arrow":"both"}],"dominantCategory":"NO_PARKING"},{"id":"ELDRIDGE_STREET_HESTER_STREET_GRAND_STREET_W_5","street":"ELDRIDGE STREET","from":"HESTER STREET","to":"GRAND STREET","side":"W","line":[[40.717226,-73.992486],[40.717307,-73.992444]],"rules":[{"category":"NO_PARKING","description":"NO PARKING MONDAY-FRIDAY 7AM-7PM <-> (SUPERSEDES R7-43R)","days":[1,2,3,4,5],"timeRanges":[{"start":420,"end":1140}],"anytime":false,"arrow":"both"},{"category":"NO_PARKING","description":"NO PARKING MONDAY-FRIDAY 7AM-7PM <-> (SUPERSEDES R7-43R)","days":[1,2,3,4,5],"timeRanges":[{"start":420,"end":1140}],"anytime":false,"arrow":"both"}],"dominantCategory":"NO_PARKING"},{"id":"ELDRIDGE_STREET_HESTER_STREET_GRAND_STREET_W_6","street":"ELDRIDGE STREET","from":"HESTER STREET","to":"GRAND STREET","side":"W","line":[[40.717307,-73.992444],[40.717563,-73.992314]],"rules":[{"category":"NO_PARKING","description":"NO PARKING MONDAY-FRIDAY 7AM-7PM <-> (SUPERSEDES R7-43R)","days":[1,2,3,4,5],"timeRanges":[{"start":420,"end":1140}],"anytime":false,"arrow":"both"}],"dominantCategory":"NO_PARKING"},{"id":"GRAND_STREET_ORCHARD_STREET_ALLEN_STREET_N_0","street":"GRAND STREET","from":"ORCHARD STREET","to":"ALLEN STREET","side":"N","line":[[40.71741,-73.991236],[40.71739,-73.99117],[40.71737,-73.99111],[40.717327,-73.990965]],"rules":[{"category":"METERED","description":"2 HMP 9AM-7PM EXCEPT SUNDAY --> (SUPERSEDES R7-182RBA)","days":[1,2,3,4,5,6],"timeRanges":[{"start":540,"end":1140}],"anytime":false,"arrow":"towards"},{"category":"ASP_DAILY","description":"NO PARKING (SANITATION BROOM SYMBOL) W/ (MOON/STARS SYMBOLS) MONDAY WEDNESDAY FRIDAY 3AM-6AM --> (SUPERSEDES SP-342CA)","days":[1,3,5],"timeRanges":[{"start":180,"end":360}],"anytime":false,"arrow":"towards"},{"category":"ASP_DAILY","description":"NO PARKING (SANITATION BROOM SYMBOL) W/ (MOON/STARS SYMBOLS) MONDAY WEDNESDAY FRIDAY 3AM-6AM <-> (SUPERSEDES SP-342C)","days":[1,3,5],"timeRanges":[{"start":180,"end":360}],"anytime":false,"arrow":"both"},{"category":"METERED","description":"2 HMP 9AM-7PM EXCEPT SUNDAY <-> (SUPERSEDES R7-182RB)","days":[1,2,3,4,5,6],"timeRanges":[{"start":540,"end":1140}],"anytime":false,"arrow":"both"}],"dominantCategory":"METERED"},{"id":"GRAND_STREET_ORCHARD_STREET_ALLEN_STREET_N_1","street":"GRAND STREET","from":"ORCHARD STREET","to":"ALLEN STREET","side":"N","line":[[40.717327,-73.990965],[40.71727,-73.99077],[40.71725,-73.9907],[40.71725,-73.9907]],"rules":[{"category":"ASP_DAILY","description":"NO PARKING (SANITATION BROOM SYMBOL) W/ (MOON/STARS SYMBOLS) MONDAY WEDNESDAY FRIDAY 3AM-6AM <-> (SUPERSEDES SP-342C)","days":[1,3,5],"timeRanges":[{"start":180,"end":360}],"anytime":false,"arrow":"both"},{"category":"METERED","description":"2 HMP 9AM-7PM EXCEPT SUNDAY <-> (SUPERSEDES R7-182RB)","days":[1,2,3,4,5,6],"timeRanges":[{"start":540,"end":1140}],"anytime":false,"arrow":"both"}],"dominantCategory":"METERED"},{"id":"GRAND_STREET_LUDLOW_STREET_ORCHARD_STREET_N_2","street":"GRAND STREET","from":"LUDLOW STREET","to":"ORCHARD STREET","side":"N","line":[[40.717201,-73.990458],[40.71725,-73.9907],[40.71725,-73.9907]],"rules":[{"category":"ASP_DAILY","description":"NO PARKING (SANITATION BROOM SYMBOL) W/ (MOON/STARS SYMBOLS) MONDAY WEDNESDAY FRIDAY 3AM-6AM <-> (SUPERSEDES SP-342C)","days":[1,3,5],"timeRanges":[{"start":180,"end":360}],"anytime":false,"arrow":"both"},{"category":"METERED","description":"2 HMP 9AM-7PM EXCEPT SUNDAY <-> (SUPERSEDES R7-182RB)","days":[1,2,3,4,5,6],"timeRanges":[{"start":540,"end":1140}],"anytime":false,"arrow":"both"}],"dominantCategory":"METERED"},{"id":"HESTER_STREET_ALLEN_STREET_ORCHARD_STREET_N_0","street":"HESTER STREET","from":"ALLEN STREET","to":"ORCHARD STREET","side":"N","line":[[40.71629,-73.99206],[40.716092,-73.991386]],"rules":[{"category":"ASP_DAILY","description":"NO PARKING (SANITATION BROOM SYMBOL) W/ (MOON/STARS SYMBOLS) MONDAY WEDNESDAY FRIDAY 3AM-6AM <-> (SUPERSEDES SP-342C)","days":[1,3,5],"timeRanges":[{"start":180,"end":360}],"anytime":false,"arrow":"both"},{"category":"NO_PARKING","description":"NO PARKING MONDAY-FRIDAY 7AM-7PM <-> (SUPERSEDES R7-43R)","days":[1,2,3,4,5],"timeRanges":[{"start":420,"end":1140}],"anytime":false,"arrow":"both"}],"dominantCategory":"NO_PARKING"},{"id":"GRAND_STREET_ELDRIDGE_STREET_FORSYTH_STREET_N_2","street":"GRAND STREET","from":"ELDRIDGE STREET","to":"FORSYTH STREET","side":"N","line":[[40.717831,-73.992623],[40.717776,-73.992442]],"rules":[{"category":"ASP_DAILY","description":"NO PARKING (SANITATION BROOM SYMBOL) W/ (MOON/STARS SYMBOLS) MONDAY WEDNESDAY FRIDAY 3AM-6AM <-> (SUPERSEDES SP-342C)","days":[1,3,5],"timeRanges":[{"start":180,"end":360}],"anytime":false,"arrow":"both"},{"category":"METERED","description":"2 HMP 9AM-7PM EXCEPT SUNDAY <-> (SUPERSEDES R7-182RB)","days":[1,2,3,4,5,6],"timeRanges":[{"start":540,"end":1140}],"anytime":false,"arrow":"both"},{"category":"METERED","description":"2 HMP 9AM-7PM EXCEPT SUNDAY <-> (SUPERSEDES R7-182RB)","days":[1,2,3,4,5,6],"timeRanges":[{"start":540,"end":1140}],"anytime":false,"arrow":"both"},{"category":"ASP_DAILY","description":"NO PARKING (SANITATION BROOM SYMBOL) W/ (MOON/STARS SYMBOLS) MONDAY WEDNESDAY FRIDAY 3AM-6AM <-> (SUPERSEDES SP-342C)","days":[1,3,5],"timeRanges":[{"start":180,"end":360}],"anytime":false,"arrow":"both"}],"dominantCategory":"METERED"},{"id":"GRAND_STREET_ELDRIDGE_STREET_FORSYTH_STREET_N_3","street":"GRAND STREET","from":"ELDRIDGE STREET","to":"FORSYTH STREET","side":"N","line":[[40.717776,-73.992442],[40.71773,-73.99229],[40.71771,-73.99222],[40.71771,-73.99222]],"rules":[{"category":"METERED","description":"2 HMP 9AM-7PM EXCEPT SUNDAY <-> (SUPERSEDES R7-182RB)","days":[1,2,3,4,5,6],"timeRanges":[{"start":540,"end":1140}],"anytime":false,"arrow":"both"},{"category":"ASP_DAILY","description":"NO PARKING (SANITATION BROOM SYMBOL) W/ (MOON/STARS SYMBOLS) MONDAY WEDNESDAY FRIDAY 3AM-6AM <-> (SUPERSEDES SP-342C)","days":[1,3,5],"timeRanges":[{"start":180,"end":360}],"anytime":false,"arrow":"both"}],"dominantCategory":"METERED"},{"id":"GRAND_STREET_FORSYTH_STREET_ELDRIDGE_STREET_S_2","street":"GRAND STREET","from":"FORSYTH STREET","to":"ELDRIDGE STREET","side":"S","line":[[40.717766,-73.992674],[40.717665,-73.992338]],"rules":[{"category":"ASP_DAILY","description":"NO PARKING (SANITATION BROOM SYMBOL) MOON & STARS (SYMBOLS) TUESDAY THURSDAY SATURDAY 3AM-6AM <-> (SUPERSEDES SP-343C)","days":[2,4,6],"timeRanges":[{"start":180,"end":360}],"anytime":false,"arrow":"both"}],"dominantCategory":"ASP_DAILY"},{"id":"ALLEN_STREET_HESTER_STREET_CANAL_STREET_W_0","street":"ALLEN STREET","from":"HESTER STREET","to":"CANAL STREET","side":"W","line":[[40.71625,-73.9921],[40.716143,-73.992129]],"rules":[{"category":"TRUCK_LOADING","description":"TRUCK (SYMBOL) TRUCK LOADING ONLY 7AM-7PM EXCEPT SUNDAY <-> (SUPERSEDES SP-30B & SP-215B)","days":[1,2,3,4,5,6],"timeRanges":[{"start":420,"end":1140}],"anytime":false,"arrow":"both"},{"category":"ASP_OVERNIGHT_MWF","description":"NO PARKING (SANITATION BROOM SYMBOL) MOON & STARS (SYMBOLS) MONDAY WEDNESDAY FRIDAY MIDNIGHT-3AM <-> (SUPERSEDES SP-702C)","days":[1,3,5],"timeRanges":[{"start":0,"end":180}],"anytime":false,"arrow":"both"}],"dominantCategory":"TRUCK_LOADING"},{"id":"ALLEN_STREET_CANAL_STREET_HESTER_STREET_E_3","street":"ALLEN STREET","from":"CANAL STREET","to":"HESTER STREET","side":"E","line":[[40.715748,-73.992154],[40.71604,-73.992076]],"rules":[{"category":"NO_STANDING","description":"BUS STOP SIGN (BUS & HANDICAP SYMBOLS) NO STANDING W/ SINGLE ARROW","days":[1,2,3,4,5,6],"timeRanges":[],"anytime":false,"arrow":null},{"category":"ASP_OVERNIGHT_TTHS","description":"NO PARKING (SANITATION BROOM SYMBOL) MOON & STARS (SYMBOLS) TUESDAY THURSDAY SATURDAY MIDNIGHT-3AM <-> (SUPERSEDES SP-339C)","days":[2,4,6],"timeRanges":[{"start":0,"end":180}],"anytime":false,"arrow":"both"},{"category":"METERED","description":"2 HMP 9AM-7PM EXCEPT SUNDAY <-> (SUPERSEDES R7-182RB)","days":[1,2,3,4,5,6],"timeRanges":[{"start":540,"end":1140}],"anytime":false,"arrow":"both"}],"dominantCategory":"NO_STANDING"},{"id":"ALLEN_STREET_CANAL_STREET_HESTER_STREET_E_4","street":"ALLEN STREET","from":"CANAL STREET","to":"HESTER STREET","side":"E","line":[[40.71604,-73.992076],[40.71625,-73.99202],[40.71625,-73.99202]],"rules":[{"category":"ASP_OVERNIGHT_TTHS","description":"NO PARKING (SANITATION BROOM SYMBOL) MOON & STARS (SYMBOLS) TUESDAY THURSDAY SATURDAY MIDNIGHT-3AM <-> (SUPERSEDES SP-339C)","days":[2,4,6],"timeRanges":[{"start":0,"end":180}],"anytime":false,"arrow":"both"},{"category":"METERED","description":"2 HMP 9AM-7PM EXCEPT SUNDAY <-> (SUPERSEDES R7-182RB)","days":[1,2,3,4,5,6],"timeRanges":[{"start":540,"end":1140}],"anytime":false,"arrow":"both"}],"dominantCategory":"METERED"},{"id":"ALLEN_STREET_BROOME_STREET_GRAND_STREET_W_0","street":"ALLEN STREET","from":"BROOME STREET","to":"GRAND STREET","side":"W","line":[[40.71738,-73.99131],[40.71743,-73.99129],[40.71745,-73.99128],[40.717493,-73.991254]],"rules":[{"category":"ASP_OVERNIGHT_MWF","description":"NO PARKING (SANITATION BROOM SYMBOL) MOON & STARS (SYMBOLS) MONDAY WEDNESDAY FRIDAY MIDNIGHT-3AM <-> (SUPERSEDES SP-702C)","days":[1,3,5],"timeRanges":[{"start":0,"end":180}],"anytime":false,"arrow":"both"},{"category":"METERED","description":"2 HMP 10AM-7PM EXCEPT SUNDAY <-> (SUPERSEDES SP-134E)","days":[1,2,3,4,5,6],"timeRanges":[{"start":600,"end":1140}],"anytime":false,"arrow":"both"},{"category":"TRUCK_LOADING","description":"TRUCK (SYMBOL) TRUCK LOADING ONLY 7AM-10AM EXCEPT SUNDAY <-> (SUPERSEDES SP-333B)","days":[1,2,3,4,5,6],"timeRanges":[{"start":420,"end":600}],"anytime":false,"arrow":"both"}],"dominantCategory":"TRUCK_LOADING"},{"id":"ALLEN_STREET_BROOME_STREET_GRAND_STREET_W_1","street":"ALLEN STREET","from":"BROOME STREET","to":"GRAND STREET","side":"W","line":[[40.717493,-73.991254],[40.7175,-73.99125],[40.71755,-73.9912],[40.71761,-73.99117],[40.71766,-73.991144]],"rules":[{"category":"ASP_OVERNIGHT_MWF","description":"NO PARKING (SANITATION BROOM SYMBOL) MOON & STARS (SYMBOLS) MONDAY WEDNESDAY FRIDAY MIDNIGHT-3AM <-> (SUPERSEDES SP-702C)","days":[1,3,5],"timeRanges":[{"start":0,"end":180}],"anytime":false,"arrow":"both"},{"category":"METERED","description":"2 HMP 10AM-7PM EXCEPT SUNDAY <-> (SUPERSEDES SP-134E)","days":[1,2,3,4,5,6],"timeRanges":[{"start":600,"end":1140}],"anytime":false,"arrow":"both"},{"category":"TRUCK_LOADING","description":"TRUCK (SYMBOL) TRUCK LOADING ONLY 7AM-10AM EXCEPT SUNDAY <-> (SUPERSEDES SP-333B)","days":[1,2,3,4,5,6],"timeRanges":[{"start":420,"end":600}],"anytime":false,"arrow":"both"},{"category":"ASP_OVERNIGHT_MWF","description":"NO PARKING (SANITATION BROOM SYMBOL) MOON & STARS (SYMBOLS) MONDAY WEDNESDAY FRIDAY MIDNIGHT-3AM <-> (SUPERSEDES SP-702C)","days":[1,3,5],"timeRanges":[{"start":0,"end":180}],"anytime":false,"arrow":"both"},{"category":"METERED","description":"2 HMP 10AM-7PM EXCEPT SUNDAY <-> (SUPERSEDES SP-134E)","days":[1,2,3,4,5,6],"timeRanges":[{"start":600,"end":1140}],"anytime":false,"arrow":"both"},{"category":"TRUCK_LOADING","description":"TRUCK (SYMBOL) TRUCK LOADING ONLY 7AM-10AM EXCEPT SUNDAY <-> (SUPERSEDES SP-333B)","days":[1,2,3,4,5,6],"timeRanges":[{"start":420,"end":600}],"anytime":false,"arrow":"both"}],"dominantCategory":"TRUCK_LOADING"},{"id":"ALLEN_STREET_BROOME_STREET_GRAND_STREET_W_2","street":"ALLEN STREET","from":"BROOME STREET","to":"GRAND STREET","side":"W","line":[[40.71766,-73.991144],[40.717844,-73.991051]],"rules":[{"category":"ASP_OVERNIGHT_MWF","description":"NO PARKING (SANITATION BROOM SYMBOL) MOON & STARS (SYMBOLS) MONDAY WEDNESDAY FRIDAY MIDNIGHT-3AM <-> (SUPERSEDES SP-702C)","days":[1,3,5],"timeRanges":[{"start":0,"end":180}],"anytime":false,"arrow":"both"},{"category":"METERED","description":"2 HMP 10AM-7PM EXCEPT SUNDAY <-> (SUPERSEDES SP-134E)","days":[1,2,3,4,5,6],"timeRanges":[{"start":600,"end":1140}],"anytime":false,"arrow":"both"},{"category":"TRUCK_LOADING","description":"TRUCK (SYMBOL) TRUCK LOADING ONLY 7AM-10AM EXCEPT SUNDAY <-> (SUPERSEDES SP-333B)","days":[1,2,3,4,5,6],"timeRanges":[{"start":420,"end":600}],"anytime":false,"arrow":"both"},{"category":"METERED","description":"2 HMP 10AM-7PM EXCEPT SUNDAY <-> (SUPERSEDES SP-134E)","days":[1,2,3,4,5,6],"timeRanges":[{"start":600,"end":1140}],"anytime":false,"arrow":"both"},{"category":"TRUCK_LOADING","description":"TRUCK (SYMBOL) TRUCK LOADING ONLY 7AM-10AM EXCEPT SUNDAY <-> (SUPERSEDES SP-333B)","days":[1,2,3,4,5,6],"timeRanges":[{"start":420,"end":600}],"anytime":false,"arrow":"both"},{"category":"ASP_OVERNIGHT_MWF","description":"NO PARKING (SANITATION BROOM SYMBOL) MOON & STARS (SYMBOLS) MONDAY WEDNESDAY FRIDAY MIDNIGHT-3AM <-> (SUPERSEDES SP-702C)","days":[1,3,5],"timeRanges":[{"start":0,"end":180}],"anytime":false,"arrow":"both"}],"dominantCategory":"TRUCK_LOADING"},{"id":"ALLEN_STREET_BROOME_STREET_GRAND_STREET_W_3","street":"ALLEN STREET","from":"BROOME STREET","to":"GRAND STREET","side":"W","line":[[40.717844,-73.991051],[40.718069,-73.990936]],"rules":[{"category":"METERED","description":"2 HMP 10AM-7PM EXCEPT SUNDAY <-> (SUPERSEDES SP-134E)","days":[1,2,3,4,5,6],"timeRanges":[{"start":600,"end":1140}],"anytime":false,"arrow":"both"},{"category":"TRUCK_LOADING","description":"TRUCK (SYMBOL) TRUCK LOADING ONLY 7AM-10AM EXCEPT SUNDAY <-> (SUPERSEDES SP-333B)","days":[1,2,3,4,5,6],"timeRanges":[{"start":420,"end":600}],"anytime":false,"arrow":"both"},{"category":"ASP_OVERNIGHT_MWF","description":"NO PARKING (SANITATION BROOM SYMBOL) MOON & STARS (SYMBOLS) MONDAY WEDNESDAY FRIDAY MIDNIGHT-3AM <-> (SUPERSEDES SP-702C)","days":[1,3,5],"timeRanges":[{"start":0,"end":180}],"anytime":false,"arrow":"both"},{"category":"METERED","description":"2 HMP 10AM-7PM EXCEPT SUNDAY <-> (SUPERSEDES SP-134E)","days":[1,2,3,4,5,6],"timeRanges":[{"start":600,"end":1140}],"anytime":false,"arrow":"both"},{"category":"ASP_OVERNIGHT_MWF","description":"NO PARKING (SANITATION BROOM SYMBOL) MOON & STARS (SYMBOLS) MONDAY WEDNESDAY FRIDAY MIDNIGHT-3AM <-> (SUPERSEDES SP-702C)","days":[1,3,5],"timeRanges":[{"start":0,"end":180}],"anytime":false,"arrow":"both"}],"dominantCategory":"TRUCK_LOADING"},{"id":"HESTER_STREET_ALLEN_STREET_ORCHARD_STREET_S_0","street":"HESTER STREET","from":"ALLEN STREET","to":"ORCHARD STREET","side":"S","line":[[40.71621,-73.99206],[40.716012,-73.991386]],"rules":[{"category":"ASP_DAILY","description":"NO PARKING (SANITATION BROOM SYMBOL) MOON & STARS (SYMBOLS) TUESDAY THURSDAY SATURDAY 3AM-6AM <-> (SUPERSEDES SP-343C)","days":[2,4,6],"timeRanges":[{"start":180,"end":360}],"anytime":false,"arrow":"both"},{"category":"METERED","description":"2 HMP 9AM-7PM EXCEPT SUNDAY <-> (SUPERSEDES R7-182RB)","days":[1,2,3,4,5,6],"timeRanges":[{"start":540,"end":1140}],"anytime":false,"arrow":"both"}],"dominantCategory":"METERED"},{"id":"ALLEN_STREET_GRAND_STREET_HESTER_STREET_W_0","street":"ALLEN STREET","from":"GRAND STREET","to":"HESTER STREET","side":"W","line":[[40.71715,-73.991471],[40.716911,-73.991638]],"rules":[{"category":"ASP_OVERNIGHT_MWF","description":"NO PARKING (SANITATION BROOM SYMBOL) MOON & STARS (SYMBOLS) MONDAY WEDNESDAY FRIDAY MIDNIGHT-3AM --> (SUPERSEDES SP-702CA)","days":[1,3,5],"timeRanges":[{"start":0,"end":180}],"anytime":false,"arrow":"towards"},{"category":"METERED","description":"2 HMP 9AM-7PM EXCEPT SUNDAY --> (SUPERSEDES R7-182RBA)","days":[1,2,3,4,5,6],"timeRanges":[{"start":540,"end":1140}],"anytime":false,"arrow":"towards"}],"dominantCategory":"METERED"},{"id":"ALLEN_STREET_GRAND_STREET_HESTER_STREET_W_1","street":"ALLEN STREET","from":"GRAND STREET","to":"HESTER STREET","side":"W","line":[[40.716911,-73.991638],[40.71664,-73.991828]],"rules":[{"category":"NO_PARKING","description":"NO PARKING ANYTIME --> (SUPERSEDES SP-854CA)","days":[0,1,2,3,4,5,6],"timeRanges":[],"anytime":true,"arrow":"towards"},{"category":"NO_STANDING","description":"BUS STOP SIGN (BUS & HANDICAP SYMBOLS) NO STANDING W/ SINGLE ARROW","days":[1,2,3,4,5,6],"timeRanges":[],"anytime":false,"arrow":null}],"dominantCategory":"NO_STANDING"},{"id":"ALLEN_STREET_GRAND_STREET_HESTER_STREET_W_2","street":"ALLEN STREET","from":"GRAND STREET","to":"HESTER STREET","side":"W","line":[[40.71664,-73.991828],[40.716417,-73.991983]],"rules":[{"category":"NO_STANDING","description":"BUS STOP SIGN (BUS & HANDICAP SYMBOLS) NO STANDING W/ SINGLE ARROW","days":[1,2,3,4,5,6],"timeRanges":[],"anytime":false,"arrow":null},{"category":"UNKNOWN","description":"SELECT BUS SERVICE DESTINATION PANEL (TEXT TO BE MODIFIED AS REQUESTED)","days":[1,2,3,4,5,6],"timeRanges":[],"anytime":false,"arrow":null},{"category":"UNKNOWN","description":"SELECT BUS SERVICE ROUTE PANEL (TEXT TO BE MODIFIED AS REQUESTED)","days":[1,2,3,4,5,6],"timeRanges":[],"anytime":false,"arrow":null}],"dominantCategory":"NO_STANDING"},{"id":"ALLEN_STREET_GRAND_STREET_HESTER_STREET_W_3","street":"ALLEN STREET","from":"GRAND STREET","to":"HESTER STREET","side":"W","line":[[40.716417,-73.991983],[40.71625,-73.9921],[40.71625,-73.9921]],"rules":[{"category":"NO_STANDING","description":"BUS STOP SIGN (BUS & HANDICAP SYMBOLS) NO STANDING <----->","days":[1,2,3,4,5,6],"timeRanges":[],"anytime":false,"arrow":"towards"},{"category":"UNKNOWN","description":"SELECT BUS SERVICE DESTINATION PANEL (TEXT TO BE MODIFIED AS REQUESTED)","days":[1,2,3,4,5,6],"timeRanges":[],"anytime":false,"arrow":null},{"category":"UNKNOWN","description":"SELECT BUS SERVICE ROUTE PANEL (TEXT TO BE MODIFIED AS REQUESTED)","days":[1,2,3,4,5,6],"timeRanges":[],"anytime":false,"arrow":null}],"dominantCategory":"NO_STANDING"},{"id":"GRAND_STREET_ALLEN_STREET_ORCHARD_STREET_S_0","street":"GRAND STREET","from":"ALLEN STREET","to":"ORCHARD STREET","side":"S","line":[[40.71734,-73.99127],[40.71731,-73.99117],[40.717302,-73.991146]],"rules":[{"category":"ASP_DAILY","description":"NO PARKING (SANITATION BROOM SYMBOL) MOON & STARS (SYMBOLS) TUESDAY THURSDAY SATURDAY 3AM-6AM <-> (SUPERSEDES SP-343C)","days":[2,4,6],"timeRanges":[{"start":180,"end":360}],"anytime":false,"arrow":"both"},{"category":"METERED","description":"2 HMP 9AM-7PM EXCEPT SUNDAY <-> (SUPERSEDES R7-182RB)","days":[1,2,3,4,5,6],"timeRanges":[{"start":540,"end":1140}],"anytime":false,"arrow":"both"}],"dominantCategory":"METERED"},{"id":"GRAND_STREET_ALLEN_STREET_ORCHARD_STREET_S_1","street":"GRAND STREET","from":"ALLEN STREET","to":"ORCHARD STREET","side":"S","line":[[40.717302,-73.991146],[40.71729,-73.99111],[40.717232,-73.990914]],"rules":[{"category":"ASP_DAILY","description":"NO PARKING (SANITATION BROOM SYMBOL) MOON & STARS (SYMBOLS) TUESDAY THURSDAY SATURDAY 3AM-6AM <-> (SUPERSEDES SP-343C)","days":[2,4,6],"timeRanges":[{"start":180,"end":360}],"anytime":false,"arrow":"both"},{"category":"METERED","description":"2 HMP 9AM-7PM EXCEPT SUNDAY <-> (SUPERSEDES R7-182RB)","days":[1,2,3,4,5,6],"timeRanges":[{"start":540,"end":1140}],"anytime":false,"arrow":"both"},{"category":"METERED","description":"2 HMP 9AM-7PM EXCEPT SUNDAY <-> (SUPERSEDES R7-182RB)","days":[1,2,3,4,5,6],"timeRanges":[{"start":540,"end":1140}],"anytime":false,"arrow":"both"},{"category":"ASP_DAILY","description":"NO PARKING (SANITATION BROOM SYMBOL) MOON & STARS (SYMBOLS) TUESDAY THURSDAY SATURDAY 3AM-6AM <-> (SUPERSEDES SP-343C)","days":[2,4,6],"timeRanges":[{"start":180,"end":360}],"anytime":false,"arrow":"both"}],"dominantCategory":"METERED"},{"id":"GRAND_STREET_ALLEN_STREET_ORCHARD_STREET_S_2","street":"GRAND STREET","from":"ALLEN STREET","to":"ORCHARD STREET","side":"S","line":[[40.717232,-73.990914],[40.71719,-73.99077],[40.71717,-73.9907],[40.71717,-73.9907]],"rules":[{"category":"METERED","description":"2 HMP 9AM-7PM EXCEPT SUNDAY <-> (SUPERSEDES R7-182RB)","days":[1,2,3,4,5,6],"timeRanges":[{"start":540,"end":1140}],"anytime":false,"arrow":"both"},{"category":"ASP_DAILY","description":"NO PARKING (SANITATION BROOM SYMBOL) MOON & STARS (SYMBOLS) TUESDAY THURSDAY SATURDAY 3AM-6AM <-> (SUPERSEDES SP-343C)","days":[2,4,6],"timeRanges":[{"start":180,"end":360}],"anytime":false,"arrow":"both"}],"dominantCategory":"METERED"},{"id":"ELDRIDGE_STREET_HESTER_STREET_GRAND_STREET_E_0","street":"ELDRIDGE STREET","from":"HESTER STREET","to":"GRAND STREET","side":"E","line":[[40.71649,-73.99278],[40.71653,-73.99276],[40.716858,-73.992593]],"rules":[{"category":"ASP_DAILY","description":"NO PARKING (SANITATION BROOM SYMBOL) 8:30AM-9AM EXCEPT SUNDAY <-> (SUPERSEDES SP-855C)","days":[1,2,3,4,5,6],"timeRanges":[{"start":510,"end":540}],"anytime":false,"arrow":"both"}],"dominantCategory":"ASP_DAILY"},{"id":"ELDRIDGE_STREET_HESTER_STREET_GRAND_STREET_E_1","street":"ELDRIDGE STREET","from":"HESTER STREET","to":"GRAND STREET","side":"E","line":[[40.716858,-73.992593],[40.717057,-73.992491]],"rules":[{"category":"ASP_DAILY","description":"NO PARKING (SANITATION BROOM SYMBOL) 8:30AM-9AM EXCEPT SUNDAY <-> (SUPERSEDES SP-855C)","days":[1,2,3,4,5,6],"timeRanges":[{"start":510,"end":540}],"anytime":false,"arrow":"both"},{"category":"ASP_DAILY","description":"NO PARKING (SANITATION BROOM SYMBOL) 8:30AM-9AM EXCEPT SUNDAY <-> (SUPERSEDES SP-855C)","days":[1,2,3,4,5,6],"timeRanges":[{"start":510,"end":540}],"anytime":false,"arrow":"both"}],"dominantCategory":"ASP_DAILY"},{"id":"ELDRIDGE_STREET_HESTER_STREET_GRAND_STREET_E_2","street":"ELDRIDGE STREET","from":"HESTER STREET","to":"GRAND STREET","side":"E","line":[[40.717057,-73.992491],[40.717479,-73.992277]],"rules":[{"category":"METERED","description":"2 HMP 9AM-7PM EXCEPT SUNDAY --> (SUPERSEDES R7-182RBA)","days":[1,2,3,4,5,6],"timeRanges":[{"start":540,"end":1140}],"anytime":false,"arrow":"towards"},{"category":"ASP_DAILY","description":"NO PARKING (SANITATION BROOM SYMBOL) 8:30AM-9AM EXCEPT SUNDAY <-> (SUPERSEDES SP-855C)","days":[1,2,3,4,5,6],"timeRanges":[{"start":510,"end":540}],"anytime":false,"arrow":"both"},{"category":"METERED","description":"2 HMP 9AM-7PM EXCEPT SUNDAY <-> (SUPERSEDES R7-182RB)","days":[1,2,3,4,5,6],"timeRanges":[{"start":540,"end":1140}],"anytime":false,"arrow":"both"},{"category":"ASP_DAILY","description":"NO PARKING (SANITATION BROOM SYMBOL) 8:30AM-9AM EXCEPT SUNDAY <-> (SUPERSEDES SP-855C)","days":[1,2,3,4,5,6],"timeRanges":[{"start":510,"end":540}],"anytime":false,"arrow":"both"}],"dominantCategory":"METERED"},{"id":"ELDRIDGE_STREET_HESTER_STREET_GRAND_STREET_E_3","street":"ELDRIDGE STREET","from":"HESTER STREET","to":"GRAND STREET","side":"E","line":[[40.717479,-73.992277],[40.71759,-73.99222],[40.71767,-73.99218],[40.71767,-73.99218]],"rules":[{"category":"METERED","description":"2 HMP 9AM-7PM EXCEPT SUNDAY <-> (SUPERSEDES R7-182RB)","days":[1,2,3,4,5,6],"timeRanges":[{"start":540,"end":1140}],"anytime":false,"arrow":"both"},{"category":"ASP_DAILY","description":"NO PARKING (SANITATION BROOM SYMBOL) 8:30AM-9AM EXCEPT SUNDAY <-> (SUPERSEDES SP-855C)","days":[1,2,3,4,5,6],"timeRanges":[{"start":510,"end":540}],"anytime":false,"arrow":"both"}],"dominantCategory":"METERED"},{"id":"ALLEN_STREET_HESTER_STREET_GRAND_STREET_E_0","street":"ALLEN STREET","from":"HESTER STREET","to":"GRAND STREET","side":"E","line":[[40.71625,-73.99202],[40.716446,-73.991883]],"rules":[{"category":"METERED","description":"2 HMP 9AM-7PM EXCEPT SUNDAY <-> (SUPERSEDES R7-182RB)","days":[1,2,3,4,5,6],"timeRanges":[{"start":540,"end":1140}],"anytime":false,"arrow":"both"},{"category":"ASP_OVERNIGHT_TTHS","description":"NO PARKING (SANITATION BROOM SYMBOL) MOON & STARS (SYMBOLS) TUESDAY THURSDAY SATURDAY MIDNIGHT-3AM <-> (SUPERSEDES SP-339C)","days":[2,4,6],"timeRanges":[{"start":0,"end":180}],"anytime":false,"arrow":"both"}],"dominantCategory":"METERED"},{"id":"ALLEN_STREET_HESTER_STREET_GRAND_STREET_E_1","street":"ALLEN STREET","from":"HESTER STREET","to":"GRAND STREET","side":"E","line":[[40.716446,-73.991883],[40.716591,-73.991782]],"rules":[{"category":"METERED","description":"2 HMP 9AM-7PM EXCEPT SUNDAY <-> (SUPERSEDES R7-182RB)","days":[1,2,3,4,5,6],"timeRanges":[{"start":540,"end":1140}],"anytime":false,"arrow":"both"},{"category":"ASP_OVERNIGHT_TTHS","description":"NO PARKING (SANITATION BROOM SYMBOL) MOON & STARS (SYMBOLS) TUESDAY THURSDAY SATURDAY MIDNIGHT-3AM <-> (SUPERSEDES SP-339C)","days":[2,4,6],"timeRanges":[{"start":0,"end":180}],"anytime":false,"arrow":"both"},{"category":"ASP_OVERNIGHT_TTHS","description":"NO PARKING (SANITATION BROOM SYMBOL) MOON & STARS (SYMBOLS) TUESDAY THURSDAY SATURDAY MIDNIGHT-3AM <-> (SUPERSEDES SP-339C)","days":[2,4,6],"timeRanges":[{"start":0,"end":180}],"anytime":false,"arrow":"both"},{"category":"METERED","description":"2 HMP 9AM-7PM EXCEPT SUNDAY <-> (SUPERSEDES R7-182RB)","days":[1,2,3,4,5,6],"timeRanges":[{"start":540,"end":1140}],"anytime":false,"arrow":"both"}],"dominantCategory":"METERED"},{"id":"ALLEN_STREET_HESTER_STREET_GRAND_STREET_E_2","street":"ALLEN STREET","from":"HESTER STREET","to":"GRAND STREET","side":"E","line":[[40.716591,-73.991782],[40.71679,-73.991643]],"rules":[{"category":"ASP_OVERNIGHT_TTHS","description":"NO PARKING (SANITATION BROOM SYMBOL) MOON & STARS (SYMBOLS) TUESDAY THURSDAY SATURDAY MIDNIGHT-3AM <-> (SUPERSEDES SP-339C)","days":[2,4,6],"timeRanges":[{"start":0,"end":180}],"anytime":false,"arrow":"both"},{"category":"METERED","description":"2 HMP 9AM-7PM EXCEPT SUNDAY <-> (SUPERSEDES R7-182RB)","days":[1,2,3,4,5,6],"timeRanges":[{"start":540,"end":1140}],"anytime":false,"arrow":"both"}],"dominantCategory":"METERED"},{"id":"ALLEN_STREET_HESTER_STREET_GRAND_STREET_E_3","street":"ALLEN STREET","from":"HESTER STREET","to":"GRAND STREET","side":"E","line":[[40.71679,-73.991643],[40.716971,-73.991516]],"rules":[{"category":"METERED","description":"2 HMP 9AM-7PM EXCEPT SUNDAY --> (SUPERSEDES R7-182RBA)","days":[1,2,3,4,5,6],"timeRanges":[{"start":540,"end":1140}],"anytime":false,"arrow":"towards"},{"category":"ASP_OVERNIGHT_TTHS","description":"NO PARKING (SANITATION BROOM SYMBOL) MOON & STARS (SYMBOLS) TUESDAY THURSDAY SATURDAY MIDNIGHT-3AM --> (SUPERSEDES SP-339CA)","days":[2,4,6],"timeRanges":[{"start":0,"end":180}],"anytime":false,"arrow":"towards"},{"category":"NO_STANDING","description":"BUS STOP SIGN (BUS & HANDICAP SYMBOLS) NO STANDING W/ SINGLE ARROW","days":[1,2,3,4,5,6],"timeRanges":[],"anytime":false,"arrow":null}],"dominantCategory":"NO_STANDING"},{"id":"ALLEN_STREET_HESTER_STREET_GRAND_STREET_E_4","street":"ALLEN STREET","from":"HESTER STREET","to":"GRAND STREET","side":"E","line":[[40.716971,-73.991516],[40.717218,-73.991343]],"rules":[{"category":"NO_STANDING","description":"BUS STOP SIGN (BUS & HANDICAP SYMBOLS) NO STANDING W/ SINGLE ARROW","days":[1,2,3,4,5,6],"timeRanges":[],"anytime":false,"arrow":null},{"category":"UNKNOWN","description":"SELECT BUS SERVICE ROUTE PANEL (TEXT TO BE MODIFIED AS REQUESTED)","days":[1,2,3,4,5,6],"timeRanges":[],"anytime":false,"arrow":null},{"category":"UNKNOWN","description":"SELECT BUS SERVICE DESTINATION PANEL (TEXT TO BE MODIFIED AS REQUESTED)","days":[1,2,3,4,5,6],"timeRanges":[],"anytime":false,"arrow":null}],"dominantCategory":"NO_STANDING"},{"id":"ALLEN_STREET_HESTER_STREET_GRAND_STREET_E_5","street":"ALLEN STREET","from":"HESTER STREET","to":"GRAND STREET","side":"E","line":[[40.717218,-73.991343],[40.71738,-73.99123],[40.71738,-73.99123]],"rules":[{"category":"UNKNOWN","description":"SELECT BUS SERVICE ROUTE PANEL (TEXT TO BE MODIFIED AS REQUESTED)","days":[1,2,3,4,5,6],"timeRanges":[],"anytime":false,"arrow":null},{"category":"UNKNOWN","description":"SELECT BUS SERVICE DESTINATION PANEL (TEXT TO BE MODIFIED AS REQUESTED)","days":[1,2,3,4,5,6],"timeRanges":[],"anytime":false,"arrow":null},{"category":"NO_STANDING","description":"BUS STOP SIGN (BUS & HANDICAP SYMBOLS) NO STANDING <----->","days":[1,2,3,4,5,6],"timeRanges":[],"anytime":false,"arrow":"towards"}],"dominantCategory":"NO_STANDING"},{"id":"GRAND_STREET_ELDRIDGE_STREET_ALLEN_STREET_S_0","street":"GRAND STREET","from":"ELDRIDGE STREET","to":"ALLEN STREET","side":"S","line":[[40.71763,-73.99222],[40.71761,-73.99216],[40.717607,-73.99215]],"rules":[{"category":"METERED","description":"2 HMP 9AM-7PM EXCEPT SUNDAY <-> (SUPERSEDES R7-182RB)","days":[1,2,3,4,5,6],"timeRanges":[{"start":540,"end":1140}],"anytime":false,"arrow":"both"},{"category":"ASP_DAILY","description":"NO PARKING (SANITATION BROOM SYMBOL) MOON & STARS (SYMBOLS) TUESDAY THURSDAY SATURDAY 3AM-6AM <-> (SUPERSEDES SP-343C)","days":[2,4,6],"timeRanges":[{"start":180,"end":360}],"anytime":false,"arrow":"both"}],"dominantCategory":"METERED"},{"id":"GRAND_STREET_ELDRIDGE_STREET_ALLEN_STREET_S_1","street":"GRAND STREET","from":"ELDRIDGE STREET","to":"ALLEN STREET","side":"S","line":[[40.717607,-73.99215],[40.717467,-73.991687]],"rules":[{"category":"METERED","description":"2 HMP 9AM-7PM EXCEPT SUNDAY <-> (SUPERSEDES R7-182RB)","days":[1,2,3,4,5,6],"timeRanges":[{"start":540,"end":1140}],"anytime":false,"arrow":"both"},{"category":"ASP_DAILY","description":"NO PARKING (SANITATION BROOM SYMBOL) MOON & STARS (SYMBOLS) TUESDAY THURSDAY SATURDAY 3AM-6AM <-> (SUPERSEDES SP-343C)","days":[2,4,6],"timeRanges":[{"start":180,"end":360}],"anytime":false,"arrow":"both"},{"category":"ASP_DAILY","description":"NO PARKING (SANITATION BROOM SYMBOL) MOON & STARS (SYMBOLS) TUESDAY THURSDAY SATURDAY 3AM-6AM <-> (SUPERSEDES SP-343C)","days":[2,4,6],"timeRanges":[{"start":180,"end":360}],"anytime":false,"arrow":"both"},{"category":"METERED","description":"2 HMP 9AM-7PM EXCEPT SUNDAY <-> (SUPERSEDES R7-182RB)","days":[1,2,3,4,5,6],"timeRanges":[{"start":540,"end":1140}],"anytime":false,"arrow":"both"}],"dominantCategory":"METERED"},{"id":"GRAND_STREET_ELDRIDGE_STREET_ALLEN_STREET_S_2","street":"GRAND STREET","from":"ELDRIDGE STREET","to":"ALLEN STREET","side":"S","line":[[40.717467,-73.991687],[40.71742,-73.99153],[40.7174,-73.99145],[40.71737,-73.99136],[40.717366,-73.991352]],"rules":[{"category":"ASP_DAILY","description":"NO PARKING (SANITATION BROOM SYMBOL) MOON & STARS (SYMBOLS) TUESDAY THURSDAY SATURDAY 3AM-6AM <-> (SUPERSEDES SP-343C)","days":[2,4,6],"timeRanges":[{"start":180,"end":360}],"anytime":false,"arrow":"both"},{"category":"METERED","description":"2 HMP 9AM-7PM EXCEPT SUNDAY <-> (SUPERSEDES R7-182RB)","days":[1,2,3,4,5,6],"timeRanges":[{"start":540,"end":1140}],"anytime":false,"arrow":"both"}],"dominantCategory":"METERED"},{"id":"ELDRIDGE_STREET_GRAND_STREET_BROOME_STREET_W_0","street":"ELDRIDGE STREET","from":"GRAND STREET","to":"BROOME STREET","side":"W","line":[[40.717776,-73.992202],[40.717911,-73.992132]],"rules":[{"category":"NO_PARKING","description":"NO PARKING MONDAY-FRIDAY 7AM-7PM --> (SUPERSEDES R7-43RA)","days":[1,2,3,4,5],"timeRanges":[{"start":420,"end":1140}],"anytime":false,"arrow":"towards"},{"category":"METERED","description":"2 HMP SATURDAY 9AM-7PM -->","days":[6],"timeRanges":[{"start":540,"end":1140}],"anytime":false,"arrow":"towards"},{"category":"NO_PARKING","description":"NO PARKING MONDAY-FRIDAY 7AM-7PM <-> (SUPERSEDES R7-43R)","days":[1,2,3,4,5],"timeRanges":[{"start":420,"end":1140}],"anytime":false,"arrow":"both"},{"category":"METERED","description":"2 HMP SATURDAY 9AM-7PM <->","days":[6],"timeRanges":[{"start":540,"end":1140}],"anytime":false,"arrow":"both"}],"dominantCategory":"NO_PARKING"},{"id":"ELDRIDGE_STREET_GRAND_STREET_BROOME_STREET_W_1","street":"ELDRIDGE STREET","from":"GRAND STREET","to":"BROOME STREET","side":"W","line":[[40.717911,-73.992132],[40.718128,-73.992021]],"rules":[{"category":"NO_PARKING","description":"NO PARKING MONDAY-FRIDAY 7AM-7PM <-> (SUPERSEDES R7-43R)","days":[1,2,3,4,5],"timeRanges":[{"start":420,"end":1140}],"anytime":false,"arrow":"both"},{"category":"METERED","description":"2 HMP SATURDAY 9AM-7PM <->","days":[6],"timeRanges":[{"start":540,"end":1140}],"anytime":false,"arrow":"both"},{"category":"NO_PARKING","description":"NO PARKING MONDAY-FRIDAY 7AM-7PM <-> (SUPERSEDES R7-43R)","days":[1,2,3,4,5],"timeRanges":[{"start":420,"end":1140}],"anytime":false,"arrow":"both"},{"category":"METERED","description":"2 HMP SATURDAY 9AM-7PM <->","days":[6],"timeRanges":[{"start":540,"end":1140}],"anytime":false,"arrow":"both"}],"dominantCategory":"NO_PARKING"},{"id":"GRAND_STREET_ALLEN_STREET_ELDRIDGE_STREET_N_0","street":"GRAND STREET","from":"ALLEN STREET","to":"ELDRIDGE STREET","side":"N","line":[[40.71771,-73.99222],[40.71769,-73.99216],[40.717611,-73.991899]],"rules":[{"category":"METERED","description":"2 HMP 9AM-7PM EXCEPT SUNDAY <-> (SUPERSEDES R7-182RB)","days":[1,2,3,4,5,6],"timeRanges":[{"start":540,"end":1140}],"anytime":false,"arrow":"both"},{"category":"ASP_DAILY","description":"NO PARKING (SANITATION BROOM SYMBOL) W/ (MOON/STARS SYMBOLS) MONDAY WEDNESDAY FRIDAY 3AM-6AM <-> (SUPERSEDES SP-342C)","days":[1,3,5],"timeRanges":[{"start":180,"end":360}],"anytime":false,"arrow":"both"}],"dominantCategory":"METERED"},{"id":"GRAND_STREET_ALLEN_STREET_ELDRIDGE_STREET_N_1","street":"GRAND STREET","from":"ALLEN STREET","to":"ELDRIDGE STREET","side":"N","line":[[40.717611,-73.991899],[40.717545,-73.99168]],"rules":[{"category":"METERED","description":"2 HMP 9AM-7PM EXCEPT SUNDAY <-> (SUPERSEDES R7-182RB)","days":[1,2,3,4,5,6],"timeRanges":[{"start":540,"end":1140}],"anytime":false,"arrow":"both"},{"category":"ASP_DAILY","description":"NO PARKING (SANITATION BROOM SYMBOL) W/ (MOON/STARS SYMBOLS) MONDAY WEDNESDAY FRIDAY 3AM-6AM <-> (SUPERSEDES SP-342C)","days":[1,3,5],"timeRanges":[{"start":180,"end":360}],"anytime":false,"arrow":"both"},{"category":"METERED","description":"2 HMP 9AM-7PM EXCEPT SUNDAY <-> (SUPERSEDES R7-182RB)","days":[1,2,3,4,5,6],"timeRanges":[{"start":540,"end":1140}],"anytime":false,"arrow":"both"},{"category":"ASP_DAILY","description":"NO PARKING (SANITATION BROOM SYMBOL) W/ (MOON/STARS SYMBOLS) MONDAY WEDNESDAY FRIDAY 3AM-6AM <-> (SUPERSEDES SP-342C)","days":[1,3,5],"timeRanges":[{"start":180,"end":360}],"anytime":false,"arrow":"both"}],"dominantCategory":"METERED"},{"id":"GRAND_STREET_ALLEN_STREET_ELDRIDGE_STREET_N_2","street":"GRAND STREET","from":"ALLEN STREET","to":"ELDRIDGE STREET","side":"N","line":[[40.717545,-73.99168],[40.7175,-73.99153],[40.71748,-73.99145],[40.71745,-73.99136],[40.717443,-73.991346]],"rules":[{"category":"METERED","description":"2 HMP 9AM-7PM EXCEPT SUNDAY <-> (SUPERSEDES R7-182RB)","days":[1,2,3,4,5,6],"timeRanges":[{"start":540,"end":1140}],"anytime":false,"arrow":"both"},{"category":"ASP_DAILY","description":"NO PARKING (SANITATION BROOM SYMBOL) W/ (MOON/STARS SYMBOLS) MONDAY WEDNESDAY FRIDAY 3AM-6AM <-> (SUPERSEDES SP-342C)","days":[1,3,5],"timeRanges":[{"start":180,"end":360}],"anytime":false,"arrow":"both"}],"dominantCategory":"METERED"},{"id":"ORCHARD_STREET_GRAND_STREET_BROOME_STREET_E_0","street":"ORCHARD STREET","from":"GRAND STREET","to":"BROOME STREET","side":"E","line":[[40.71721,-73.99066],[40.71728,-73.99063],[40.71751,-73.990512]],"rules":[{"category":"ASP_OVERNIGHT_TTHS","description":"NO PARKING (SANITATION BROOM SYMBOL) MOON & STARS (SYMBOLS) TUESDAY THURSDAY SATURDAY MIDNIGHT-3AM <-> (SUPERSEDES SP-339C)","days":[2,4,6],"timeRanges":[{"start":0,"end":180}],"anytime":false,"arrow":"both"},{"category":"NO_PARKING","description":"NO PARKING 7AM-7PM EXCEPT SUNDAY <-> (SUPERSEDES R7-42R)","days":[1,2,3,4,5,6],"timeRanges":[{"start":420,"end":1140}],"anytime":false,"arrow":"both"}],"dominantCategory":"NO_PARKING"},{"id":"HESTER_STREET_ELDRIDGE_STREET_ALLEN_STREET_N_0","street":"HESTER STREET","from":"ELDRIDGE STREET","to":"ALLEN STREET","side":"N","line":[[40.716353,-73.99224],[40.716377,-73.99232]],"rules":[{"category":"NO_STANDING","description":"NO STANDING FIRE ZONE --> (SUPERSEDES SP-453BA)","days":[1,2,3,4,5,6],"timeRanges":[],"anytime":false,"arrow":"towards"},{"category":"ASP_DAILY","description":"NO PARKING (SANITATION BROOM SYMBOL) W/ (MOON/STARS SYMBOLS) MONDAY WEDNESDAY FRIDAY 3AM-6AM <-> (SUPERSEDES SP-342C)","days":[1,3,5],"timeRanges":[{"start":180,"end":360}],"anytime":false,"arrow":"both"},{"category":"METERED","description":"2 HMP 9AM-7PM EXCEPT SUNDAY <-> (SUPERSEDES R7-182RB)","days":[1,2,3,4,5,6],"timeRanges":[{"start":540,"end":1140}],"anytime":false,"arrow":"both"}],"dominantCategory":"NO_STANDING"},{"id":"HESTER_STREET_ELDRIDGE_STREET_ALLEN_STREET_N_1","street":"HESTER STREET","from":"ELDRIDGE STREET","to":"ALLEN STREET","side":"N","line":[[40.716377,-73.99232],[40.716456,-73.992582]],"rules":[{"category":"ASP_DAILY","description":"NO PARKING (SANITATION BROOM SYMBOL) W/ (MOON/STARS SYMBOLS) MONDAY WEDNESDAY FRIDAY 3AM-6AM <-> (SUPERSEDES SP-342C)","days":[1,3,5],"timeRanges":[{"start":180,"end":360}],"anytime":false,"arrow":"both"},{"category":"METERED","description":"2 HMP 9AM-7PM EXCEPT SUNDAY <-> (SUPERSEDES R7-182RB)","days":[1,2,3,4,5,6],"timeRanges":[{"start":540,"end":1140}],"anytime":false,"arrow":"both"},{"category":"ASP_DAILY","description":"NO PARKING (SANITATION BROOM SYMBOL) W/ (MOON/STARS SYMBOLS) MONDAY WEDNESDAY FRIDAY 3AM-6AM <-> (SUPERSEDES SP-342C)","days":[1,3,5],"timeRanges":[{"start":180,"end":360}],"anytime":false,"arrow":"both"},{"category":"METERED","description":"2 HMP 9AM-7PM EXCEPT SUNDAY <-> (SUPERSEDES R7-182RB)","days":[1,2,3,4,5,6],"timeRanges":[{"start":540,"end":1140}],"anytime":false,"arrow":"both"}],"dominantCategory":"METERED"},{"id":"HESTER_STREET_ELDRIDGE_STREET_ALLEN_STREET_N_2","street":"HESTER STREET","from":"ELDRIDGE STREET","to":"ALLEN STREET","side":"N","line":[[40.716456,-73.992582],[40.71651,-73.99276],[40.71653,-73.99282],[40.71653,-73.99282]],"rules":[{"category":"ASP_DAILY","description":"NO PARKING (SANITATION BROOM SYMBOL) W/ (MOON/STARS SYMBOLS) MONDAY WEDNESDAY FRIDAY 3AM-6AM <-> (SUPERSEDES SP-342C)","days":[1,3,5],"timeRanges":[{"start":180,"end":360}],"anytime":false,"arrow":"both"},{"category":"METERED","description":"2 HMP 9AM-7PM EXCEPT SUNDAY <-> (SUPERSEDES R7-182RB)","days":[1,2,3,4,5,6],"timeRanges":[{"start":540,"end":1140}],"anytime":false,"arrow":"both"}],"dominantCategory":"METERED"},{"id":"ORCHARD_STREET_HESTER_STREET_GRAND_STREET_E_0","street":"ORCHARD STREET","from":"HESTER STREET","to":"GRAND STREET","side":"E","line":[[40.71603,-73.99127],[40.71608,-73.99125],[40.716278,-73.991145]],"rules":[{"category":"ASP_OVERNIGHT_TTHS","description":"NO PARKING (SANITATION BROOM SYMBOL) MOON & STARS (SYMBOLS) TUESDAY THURSDAY SATURDAY MIDNIGHT-3AM <-> (SUPERSEDES SP-339C)","days":[2,4,6],"timeRanges":[{"start":0,"end":180}],"anytime":false,"arrow":"both"},{"category":"UNKNOWN","description":"2 HOUR PARKING SATURDAY 9AM-7PM <->","days":[6],"timeRanges":[{"start":540,"end":1140}],"anytime":false,"arrow":"both"}],"dominantCategory":"ASP_OVERNIGHT_TTHS"},{"id":"ORCHARD_STREET_HESTER_STREET_GRAND_STREET_E_1","street":"ORCHARD STREET","from":"HESTER STREET","to":"GRAND STREET","side":"E","line":[[40.716278,-73.991145],[40.71661,-73.99097],[40.716761,-73.990891]],"rules":[{"category":"NO_PARKING","description":"NO PARKING MONDAY-FRIDAY 7AM-7PM --> (SUPERSEDES R7-43RA)","days":[1,2,3,4,5],"timeRanges":[{"start":420,"end":1140}],"anytime":false,"arrow":"towards"},{"category":"ASP_OVERNIGHT_TTHS","description":"NO PARKING (SANITATION BROOM SYMBOL) MOON & STARS (SYMBOLS) TUESDAY THURSDAY SATURDAY MIDNIGHT-3AM <-> (SUPERSEDES SP-339C)","days":[2,4,6],"timeRanges":[{"start":0,"end":180}],"anytime":false,"arrow":"both"},{"category":"UNKNOWN","description":"2 HOUR PARKING SATURDAY 9AM-7PM <->","days":[6],"timeRanges":[{"start":540,"end":1140}],"anytime":false,"arrow":"both"},{"category":"SPECIAL","description":"STAR (SYMBOL) AVO DEPT OF EDUCATION SCHOOL DAYS 7AM-4PM --> (SUPERSEDES PS-16EA)(PUBLIC SCHOOL SIGN)","days":[1,2,3,4,5,6],"timeRanges":[{"start":420,"end":960}],"anytime":false,"arrow":"towards"},{"category":"NO_PARKING","description":"NO PARKING MONDAY-FRIDAY 7AM-7PM <-> (SUPERSEDES R7-43R)","days":[1,2,3,4,5],"timeRanges":[{"start":420,"end":1140}],"anytime":false,"arrow":"both"},{"category":"ASP_OVERNIGHT_TTHS","description":"NO PARKING (SANITATION BROOM SYMBOL) MOON & STARS (SYMBOLS) TUESDAY THURSDAY SATURDAY MIDNIGHT-3AM <-> (SUPERSEDES SP-339C)","days":[2,4,6],"timeRanges":[{"start":0,"end":180}],"anytime":false,"arrow":"both"},{"category":"UNKNOWN","description":"2 HOUR PARKING SATURDAY 9AM-7PM <->","days":[6],"timeRanges":[{"start":540,"end":1140}],"anytime":false,"arrow":"both"}],"dominantCategory":"NO_PARKING"},{"id":"ORCHARD_STREET_HESTER_STREET_GRAND_STREET_E_2","street":"ORCHARD STREET","from":"HESTER STREET","to":"GRAND STREET","side":"E","line":[[40.716761,-73.990891],[40.717054,-73.990739]],"rules":[{"category":"NO_PARKING","description":"NO PARKING MONDAY-FRIDAY 7AM-7PM <-> (SUPERSEDES R7-43R)","days":[1,2,3,4,5],"timeRanges":[{"start":420,"end":1140}],"anytime":false,"arrow":"both"},{"category":"ASP_OVERNIGHT_TTHS","description":"NO PARKING (SANITATION BROOM SYMBOL) MOON & STARS (SYMBOLS) TUESDAY THURSDAY SATURDAY MIDNIGHT-3AM <-> (SUPERSEDES SP-339C)","days":[2,4,6],"timeRanges":[{"start":0,"end":180}],"anytime":false,"arrow":"both"},{"category":"UNKNOWN","description":"2 HOUR PARKING SATURDAY 9AM-7PM <->","days":[6],"timeRanges":[{"start":540,"end":1140}],"anytime":false,"arrow":"both"},{"category":"ASP_OVERNIGHT_TTHS","description":"NO PARKING (SANITATION BROOM SYMBOL) MOON & STARS (SYMBOLS) TUESDAY THURSDAY SATURDAY MIDNIGHT-3AM <-> (SUPERSEDES SP-339C)","days":[2,4,6],"timeRanges":[{"start":0,"end":180}],"anytime":false,"arrow":"both"},{"category":"NO_PARKING","description":"NO PARKING MONDAY-FRIDAY 7AM-7PM <-> (SUPERSEDES R7-43R)","days":[1,2,3,4,5],"timeRanges":[{"start":420,"end":1140}],"anytime":false,"arrow":"both"},{"category":"UNKNOWN","description":"2 HOUR PARKING SATURDAY 9AM-7PM <->","days":[6],"timeRanges":[{"start":540,"end":1140}],"anytime":false,"arrow":"both"}],"dominantCategory":"NO_PARKING"},{"id":"ORCHARD_STREET_HESTER_STREET_GRAND_STREET_E_3","street":"ORCHARD STREET","from":"HESTER STREET","to":"GRAND STREET","side":"E","line":[[40.717054,-73.990739],[40.71713,-73.9907],[40.71721,-73.99066],[40.71721,-73.99066]],"rules":[{"category":"ASP_OVERNIGHT_TTHS","description":"NO PARKING (SANITATION BROOM SYMBOL) MOON & STARS (SYMBOLS) TUESDAY THURSDAY SATURDAY MIDNIGHT-3AM <-> (SUPERSEDES SP-339C)","days":[2,4,6],"timeRanges":[{"start":0,"end":180}],"anytime":false,"arrow":"both"},{"category":"NO_PARKING","description":"NO PARKING MONDAY-FRIDAY 7AM-7PM <-> (SUPERSEDES R7-43R)","days":[1,2,3,4,5],"timeRanges":[{"start":420,"end":1140}],"anytime":false,"arrow":"both"},{"category":"UNKNOWN","description":"2 HOUR PARKING SATURDAY 9AM-7PM <->","days":[6],"timeRanges":[{"start":540,"end":1140}],"anytime":false,"arrow":"both"}],"dominantCategory":"NO_PARKING"}]